<?xml version="1.0" encoding="iso-8859-2"?>
<VYSLEDKY_OKRES xmlns="http://www.volby.cz/ps/" xmlns:xsi="http://www.w3.org/2001/XMLSchema-instance"
                 xsi:schemaLocation="http://www.volby.cz/ps/ ps_vysledky_okres.xsd"
                 DATUM_GENEROVANI="27/10/2013" CAS_GENEROVANI="11:42:02">
<OKRES CIS_OKRES="CZ020A" NAZ_OKRES="Praha-západ">
<UCAST OKRSKY_CELKEM="125" OKRSKY_ZPRAC="125" OKRSKY_ZPRAC_PROC="100.00" ZAPSANI_VOLICI="95032" VYDANE_OBALKY="64572" UCAST_PROC="67.95" ODEVZDANE_OBALKY="64528" PLATNE_HLASY="64007" PLATNE_HLASY_PROC="99.19"/>
<HLASY_STRANA KSTRANA="1" HLASY="7412" PROC_HLASU="11.57"/>
<HLASY_STRANA KSTRANA="2" HLASY="2131" PROC_HLASU="3.32"/>
<HLASY_STRANA KSTRANA="3" HLASY="1898" PROC_HLASU="2.96"/>
<HLASY_STRANA KSTRANA="4" HLASY="15643" PROC_HLASU="24.43"/>
<HLASY_STRANA KSTRANA="5" HLASY="378" PROC_HLASU="0.59"/>
<HLASY_STRANA KSTRANA="6" HLASY="7184" PROC_HLASU="11.22"/>
<HLASY_STRANA KSTRANA="7" HLASY="33" PROC_HLASU="0.05"/>
<HLASY_STRANA KSTRANA="9" HLASY="304" PROC_HLASU="0.47"/>
<HLASY_STRANA KSTRANA="10" HLASY="182" PROC_HLASU="0.28"/>
<HLASY_STRANA KSTRANA="11" HLASY="2720" PROC_HLASU="4.24"/>
<HLASY_STRANA KSTRANA="13" HLASY="143" PROC_HLASU="0.22"/>
<HLASY_STRANA KSTRANA="14" HLASY="36" PROC_HLASU="0.05"/>
<HLASY_STRANA KSTRANA="15" HLASY="682" PROC_HLASU="1.06"/>
<HLASY_STRANA KSTRANA="17" HLASY="2894" PROC_HLASU="4.52"/>
<HLASY_STRANA KSTRANA="18" HLASY="318" PROC_HLASU="0.49"/>
<HLASY_STRANA KSTRANA="20" HLASY="12981" PROC_HLASU="20.28"/>
<HLASY_STRANA KSTRANA="21" HLASY="5579" PROC_HLASU="8.71"/>
<HLASY_STRANA KSTRANA="22" HLASY="33" PROC_HLASU="0.05"/>
<HLASY_STRANA KSTRANA="23" HLASY="3320" PROC_HLASU="5.18"/>
<HLASY_STRANA KSTRANA="24" HLASY="136" PROC_HLASU="0.21"/>
</OKRES>
<OBEC CIS_OBEC="513458" NAZ_OBEC="Vestec">
<UCAST OKRSKY_CELKEM="1" OKRSKY_ZPRAC="1" OKRSKY_ZPRAC_PROC="100.00" ZAPSANI_VOLICI="1291" VYDANE_OBALKY="941" UCAST_PROC="72.89" ODEVZDANE_OBALKY="940" PLATNE_HLASY="926" PLATNE_HLASY_PROC="98.51" />
<HLASY_STRANA KSTRANA="1" HLASY="87" PROC_HLASU="9.39"/>
<HLASY_STRANA KSTRANA="2" HLASY="40" PROC_HLASU="4.31"/>
<HLASY_STRANA KSTRANA="3" HLASY="28" PROC_HLASU="3.02"/>
<HLASY_STRANA KSTRANA="4" HLASY="244" PROC_HLASU="26.34"/>
<HLASY_STRANA KSTRANA="5" HLASY="6" PROC_HLASU="0.64"/>
<HLASY_STRANA KSTRANA="6" HLASY="103" PROC_HLASU="11.12"/>
<HLASY_STRANA KSTRANA="9" HLASY="4" PROC_HLASU="0.43"/>
<HLASY_STRANA KSTRANA="11" HLASY="39" PROC_HLASU="4.21"/>
<HLASY_STRANA KSTRANA="13" HLASY="1" PROC_HLASU="0.10"/>
<HLASY_STRANA KSTRANA="15" HLASY="11" PROC_HLASU="1.18"/>
<HLASY_STRANA KSTRANA="17" HLASY="45" PROC_HLASU="4.85"/>
<HLASY_STRANA KSTRANA="18" HLASY="8" PROC_HLASU="0.86"/>
<HLASY_STRANA KSTRANA="20" HLASY="235" PROC_HLASU="25.37"/>
<HLASY_STRANA KSTRANA="21" HLASY="42" PROC_HLASU="4.53"/>
<HLASY_STRANA KSTRANA="23" HLASY="30" PROC_HLASU="3.23"/>
<HLASY_STRANA KSTRANA="24" HLASY="3" PROC_HLASU="0.32"/>
</OBEC>
<OBEC CIS_OBEC="539155" NAZ_OBEC="Čisovice">
<UCAST OKRSKY_CELKEM="2" OKRSKY_ZPRAC="2" OKRSKY_ZPRAC_PROC="100.00" ZAPSANI_VOLICI="790" VYDANE_OBALKY="513" UCAST_PROC="64.94" ODEVZDANE_OBALKY="513" PLATNE_HLASY="511" PLATNE_HLASY_PROC="99.61" />
<HLASY_STRANA KSTRANA="1" HLASY="90" PROC_HLASU="17.61"/>
<HLASY_STRANA KSTRANA="2" HLASY="12" PROC_HLASU="2.34"/>
<HLASY_STRANA KSTRANA="3" HLASY="13" PROC_HLASU="2.54"/>
<HLASY_STRANA KSTRANA="4" HLASY="92" PROC_HLASU="18.00"/>
<HLASY_STRANA KSTRANA="5" HLASY="4" PROC_HLASU="0.78"/>
<HLASY_STRANA KSTRANA="6" HLASY="44" PROC_HLASU="8.61"/>
<HLASY_STRANA KSTRANA="9" HLASY="3" PROC_HLASU="0.58"/>
<HLASY_STRANA KSTRANA="10" HLASY="1" PROC_HLASU="0.19"/>
<HLASY_STRANA KSTRANA="11" HLASY="18" PROC_HLASU="3.52"/>
<HLASY_STRANA KSTRANA="13" HLASY="6" PROC_HLASU="1.17"/>
<HLASY_STRANA KSTRANA="15" HLASY="5" PROC_HLASU="0.97"/>
<HLASY_STRANA KSTRANA="17" HLASY="29" PROC_HLASU="5.67"/>
<HLASY_STRANA KSTRANA="18" HLASY="3" PROC_HLASU="0.58"/>
<HLASY_STRANA KSTRANA="20" HLASY="118" PROC_HLASU="23.09"/>
<HLASY_STRANA KSTRANA="21" HLASY="54" PROC_HLASU="10.56"/>
<HLASY_STRANA KSTRANA="22" HLASY="3" PROC_HLASU="0.58"/>
<HLASY_STRANA KSTRANA="23" HLASY="13" PROC_HLASU="2.54"/>
<HLASY_STRANA KSTRANA="24" HLASY="3" PROC_HLASU="0.58"/>
</OBEC>
<OBEC CIS_OBEC="539163" NAZ_OBEC="Davle">
<UCAST OKRSKY_CELKEM="2" OKRSKY_ZPRAC="2" OKRSKY_ZPRAC_PROC="100.00" ZAPSANI_VOLICI="1205" VYDANE_OBALKY="859" UCAST_PROC="71.29" ODEVZDANE_OBALKY="859" PLATNE_HLASY="850" PLATNE_HLASY_PROC="98.95" />
<HLASY_STRANA KSTRANA="1" HLASY="99" PROC_HLASU="11.64"/>
<HLASY_STRANA KSTRANA="2" HLASY="18" PROC_HLASU="2.11"/>
<HLASY_STRANA KSTRANA="3" HLASY="37" PROC_HLASU="4.35"/>
<HLASY_STRANA KSTRANA="4" HLASY="162" PROC_HLASU="19.05"/>
<HLASY_STRANA KSTRANA="5" HLASY="7" PROC_HLASU="0.82"/>
<HLASY_STRANA KSTRANA="6" HLASY="103" PROC_HLASU="12.11"/>
<HLASY_STRANA KSTRANA="7" HLASY="1" PROC_HLASU="0.11"/>
<HLASY_STRANA KSTRANA="9" HLASY="5" PROC_HLASU="0.58"/>
<HLASY_STRANA KSTRANA="10" HLASY="6" PROC_HLASU="0.70"/>
<HLASY_STRANA KSTRANA="11" HLASY="40" PROC_HLASU="4.70"/>
<HLASY_STRANA KSTRANA="14" HLASY="1" PROC_HLASU="0.11"/>
<HLASY_STRANA KSTRANA="15" HLASY="8" PROC_HLASU="0.94"/>
<HLASY_STRANA KSTRANA="17" HLASY="44" PROC_HLASU="5.17"/>
<HLASY_STRANA KSTRANA="18" HLASY="11" PROC_HLASU="1.29"/>
<HLASY_STRANA KSTRANA="20" HLASY="191" PROC_HLASU="22.47"/>
<HLASY_STRANA KSTRANA="21" HLASY="74" PROC_HLASU="8.70"/>
<HLASY_STRANA KSTRANA="22" HLASY="1" PROC_HLASU="0.11"/>
<HLASY_STRANA KSTRANA="23" HLASY="42" PROC_HLASU="4.94"/>
</OBEC>
<OBEC CIS_OBEC="539252" NAZ_OBEC="Hradištko">
<UCAST OKRSKY_CELKEM="3" OKRSKY_ZPRAC="3" OKRSKY_ZPRAC_PROC="100.00" ZAPSANI_VOLICI="1518" VYDANE_OBALKY="1093" UCAST_PROC="72.00" ODEVZDANE_OBALKY="1093" PLATNE_HLASY="1082" PLATNE_HLASY_PROC="98.99" />
<HLASY_STRANA KSTRANA="1" HLASY="122" PROC_HLASU="11.27"/>
<HLASY_STRANA KSTRANA="2" HLASY="38" PROC_HLASU="3.51"/>
<HLASY_STRANA KSTRANA="3" HLASY="18" PROC_HLASU="1.66"/>
<HLASY_STRANA KSTRANA="4" HLASY="239" PROC_HLASU="22.08"/>
<HLASY_STRANA KSTRANA="5" HLASY="8" PROC_HLASU="0.73"/>
<HLASY_STRANA KSTRANA="6" HLASY="112" PROC_HLASU="10.35"/>
<HLASY_STRANA KSTRANA="9" HLASY="8" PROC_HLASU="0.73"/>
<HLASY_STRANA KSTRANA="10" HLASY="2" PROC_HLASU="0.18"/>
<HLASY_STRANA KSTRANA="11" HLASY="48" PROC_HLASU="4.43"/>
<HLASY_STRANA KSTRANA="13" HLASY="2" PROC_HLASU="0.18"/>
<HLASY_STRANA KSTRANA="15" HLASY="8" PROC_HLASU="0.73"/>
<HLASY_STRANA KSTRANA="17" HLASY="54" PROC_HLASU="4.99"/>
<HLASY_STRANA KSTRANA="18" HLASY="5" PROC_HLASU="0.46"/>
<HLASY_STRANA KSTRANA="20" HLASY="264" PROC_HLASU="24.39"/>
<HLASY_STRANA KSTRANA="21" HLASY="110" PROC_HLASU="10.16"/>
<HLASY_STRANA KSTRANA="22" HLASY="5" PROC_HLASU="0.46"/>
<HLASY_STRANA KSTRANA="23" HLASY="36" PROC_HLASU="3.32"/>
<HLASY_STRANA KSTRANA="24" HLASY="3" PROC_HLASU="0.27"/>
</OBEC>
<OBEC CIS_OBEC="539317" NAZ_OBEC="Jeneč">
<UCAST OKRSKY_CELKEM="1" OKRSKY_ZPRAC="1" OKRSKY_ZPRAC_PROC="100.00" ZAPSANI_VOLICI="980" VYDANE_OBALKY="600" UCAST_PROC="61.22" ODEVZDANE_OBALKY="600" PLATNE_HLASY="595" PLATNE_HLASY_PROC="99.17" />
<HLASY_STRANA KSTRANA="1" HLASY="88" PROC_HLASU="14.78"/>
<HLASY_STRANA KSTRANA="2" HLASY="16" PROC_HLASU="2.68"/>
<HLASY_STRANA KSTRANA="3" HLASY="21" PROC_HLASU="3.52"/>
<HLASY_STRANA KSTRANA="4" HLASY="79" PROC_HLASU="13.27"/>
<HLASY_STRANA KSTRANA="5" HLASY="6" PROC_HLASU="1.00"/>
<HLASY_STRANA KSTRANA="6" HLASY="40" PROC_HLASU="6.72"/>
<HLASY_STRANA KSTRANA="9" HLASY="3" PROC_HLASU="0.50"/>
<HLASY_STRANA KSTRANA="11" HLASY="9" PROC_HLASU="1.51"/>
<HLASY_STRANA KSTRANA="13" HLASY="2" PROC_HLASU="0.33"/>
<HLASY_STRANA KSTRANA="15" HLASY="4" PROC_HLASU="0.67"/>
<HLASY_STRANA KSTRANA="17" HLASY="29" PROC_HLASU="4.87"/>
<HLASY_STRANA KSTRANA="18" HLASY="5" PROC_HLASU="0.84"/>
<HLASY_STRANA KSTRANA="20" HLASY="125" PROC_HLASU="21.00"/>
<HLASY_STRANA KSTRANA="21" HLASY="143" PROC_HLASU="24.03"/>
<HLASY_STRANA KSTRANA="22" HLASY="1" PROC_HLASU="0.16"/>
<HLASY_STRANA KSTRANA="23" HLASY="22" PROC_HLASU="3.69"/>
<HLASY_STRANA KSTRANA="24" HLASY="2" PROC_HLASU="0.33"/>
</OBEC>
<OBEC CIS_OBEC="539325" NAZ_OBEC="Jesenice">
<UCAST OKRSKY_CELKEM="4" OKRSKY_ZPRAC="4" OKRSKY_ZPRAC_PROC="100.00" ZAPSANI_VOLICI="4852" VYDANE_OBALKY="3366" UCAST_PROC="69.37" ODEVZDANE_OBALKY="3361" PLATNE_HLASY="3339" PLATNE_HLASY_PROC="99.35" />
<HLASY_STRANA KSTRANA="1" HLASY="306" PROC_HLASU="9.16"/>
<HLASY_STRANA KSTRANA="2" HLASY="126" PROC_HLASU="3.77"/>
<HLASY_STRANA KSTRANA="3" HLASY="97" PROC_HLASU="2.90"/>
<HLASY_STRANA KSTRANA="4" HLASY="948" PROC_HLASU="28.39"/>
<HLASY_STRANA KSTRANA="5" HLASY="19" PROC_HLASU="0.56"/>
<HLASY_STRANA KSTRANA="6" HLASY="370" PROC_HLASU="11.08"/>
<HLASY_STRANA KSTRANA="7" HLASY="1" PROC_HLASU="0.02"/>
<HLASY_STRANA KSTRANA="9" HLASY="11" PROC_HLASU="0.32"/>
<HLASY_STRANA KSTRANA="10" HLASY="8" PROC_HLASU="0.23"/>
<HLASY_STRANA KSTRANA="11" HLASY="104" PROC_HLASU="3.11"/>
<HLASY_STRANA KSTRANA="13" HLASY="6" PROC_HLASU="0.17"/>
<HLASY_STRANA KSTRANA="14" HLASY="1" PROC_HLASU="0.02"/>
<HLASY_STRANA KSTRANA="15" HLASY="23" PROC_HLASU="0.68"/>
<HLASY_STRANA KSTRANA="17" HLASY="164" PROC_HLASU="4.91"/>
<HLASY_STRANA KSTRANA="18" HLASY="21" PROC_HLASU="0.62"/>
<HLASY_STRANA KSTRANA="20" HLASY="824" PROC_HLASU="24.67"/>
<HLASY_STRANA KSTRANA="21" HLASY="179" PROC_HLASU="5.36"/>
<HLASY_STRANA KSTRANA="23" HLASY="128" PROC_HLASU="3.83"/>
<HLASY_STRANA KSTRANA="24" HLASY="3" PROC_HLASU="0.08"/>
</OBEC>
<OBEC CIS_OBEC="539341" NAZ_OBEC="Jíloviště">
<UCAST OKRSKY_CELKEM="1" OKRSKY_ZPRAC="1" OKRSKY_ZPRAC_PROC="100.00" ZAPSANI_VOLICI="536" VYDANE_OBALKY="407" UCAST_PROC="75.93" ODEVZDANE_OBALKY="406" PLATNE_HLASY="399" PLATNE_HLASY_PROC="98.28" />
<HLASY_STRANA KSTRANA="1" HLASY="46" PROC_HLASU="11.52"/>
<HLASY_STRANA KSTRANA="2" HLASY="9" PROC_HLASU="2.25"/>
<HLASY_STRANA KSTRANA="3" HLASY="11" PROC_HLASU="2.75"/>
<HLASY_STRANA KSTRANA="4" HLASY="99" PROC_HLASU="24.81"/>
<HLASY_STRANA KSTRANA="5" HLASY="1" PROC_HLASU="0.25"/>
<HLASY_STRANA KSTRANA="6" HLASY="47" PROC_HLASU="11.77"/>
<HLASY_STRANA KSTRANA="9" HLASY="2" PROC_HLASU="0.50"/>
<HLASY_STRANA KSTRANA="11" HLASY="20" PROC_HLASU="5.01"/>
<HLASY_STRANA KSTRANA="13" HLASY="1" PROC_HLASU="0.25"/>
<HLASY_STRANA KSTRANA="14" HLASY="1" PROC_HLASU="0.25"/>
<HLASY_STRANA KSTRANA="15" HLASY="1" PROC_HLASU="0.25"/>
<HLASY_STRANA KSTRANA="17" HLASY="17" PROC_HLASU="4.26"/>
<HLASY_STRANA KSTRANA="18" HLASY="3" PROC_HLASU="0.75"/>
<HLASY_STRANA KSTRANA="20" HLASY="77" PROC_HLASU="19.29"/>
<HLASY_STRANA KSTRANA="21" HLASY="44" PROC_HLASU="11.02"/>
<HLASY_STRANA KSTRANA="22" HLASY="1" PROC_HLASU="0.25"/>
<HLASY_STRANA KSTRANA="23" HLASY="19" PROC_HLASU="4.76"/>
</OBEC>
<OBEC CIS_OBEC="539872" NAZ_OBEC="Zbuzany">
<UCAST OKRSKY_CELKEM="1" OKRSKY_ZPRAC="1" OKRSKY_ZPRAC_PROC="100.00" ZAPSANI_VOLICI="718" VYDANE_OBALKY="467" UCAST_PROC="65.04" ODEVZDANE_OBALKY="467" PLATNE_HLASY="464" PLATNE_HLASY_PROC="99.36" />
<HLASY_STRANA KSTRANA="1" HLASY="38" PROC_HLASU="8.18"/>
<HLASY_STRANA KSTRANA="2" HLASY="15" PROC_HLASU="3.23"/>
<HLASY_STRANA KSTRANA="3" HLASY="23" PROC_HLASU="4.95"/>
<HLASY_STRANA KSTRANA="4" HLASY="117" PROC_HLASU="25.21"/>
<HLASY_STRANA KSTRANA="5" HLASY="3" PROC_HLASU="0.64"/>
<HLASY_STRANA KSTRANA="6" HLASY="49" PROC_HLASU="10.56"/>
<HLASY_STRANA KSTRANA="10" HLASY="1" PROC_HLASU="0.21"/>
<HLASY_STRANA KSTRANA="11" HLASY="15" PROC_HLASU="3.23"/>
<HLASY_STRANA KSTRANA="15" HLASY="5" PROC_HLASU="1.07"/>
<HLASY_STRANA KSTRANA="17" HLASY="13" PROC_HLASU="2.80"/>
<HLASY_STRANA KSTRANA="18" HLASY="1" PROC_HLASU="0.21"/>
<HLASY_STRANA KSTRANA="20" HLASY="114" PROC_HLASU="24.56"/>
<HLASY_STRANA KSTRANA="21" HLASY="38" PROC_HLASU="8.18"/>
<HLASY_STRANA KSTRANA="22" HLASY="1" PROC_HLASU="0.21"/>
<HLASY_STRANA KSTRANA="23" HLASY="30" PROC_HLASU="6.46"/>
<HLASY_STRANA KSTRANA="24" HLASY="1" PROC_HLASU="0.21"/>
</OBEC>
<OBEC CIS_OBEC="598313" NAZ_OBEC="Trnová">
<UCAST OKRSKY_CELKEM="1" OKRSKY_ZPRAC="1" OKRSKY_ZPRAC_PROC="100.00" ZAPSANI_VOLICI="188" VYDANE_OBALKY="141" UCAST_PROC="75.00" ODEVZDANE_OBALKY="141" PLATNE_HLASY="140" PLATNE_HLASY_PROC="99.29" />
<HLASY_STRANA KSTRANA="1" HLASY="14" PROC_HLASU="10.00"/>
<HLASY_STRANA KSTRANA="2" HLASY="11" PROC_HLASU="7.85"/>
<HLASY_STRANA KSTRANA="3" HLASY="2" PROC_HLASU="1.42"/>
<HLASY_STRANA KSTRANA="4" HLASY="20" PROC_HLASU="14.28"/>
<HLASY_STRANA KSTRANA="6" HLASY="13" PROC_HLASU="9.28"/>
<HLASY_STRANA KSTRANA="11" HLASY="4" PROC_HLASU="2.85"/>
<HLASY_STRANA KSTRANA="15" HLASY="2" PROC_HLASU="1.42"/>
<HLASY_STRANA KSTRANA="17" HLASY="9" PROC_HLASU="6.42"/>
<HLASY_STRANA KSTRANA="18" HLASY="1" PROC_HLASU="0.71"/>
<HLASY_STRANA KSTRANA="20" HLASY="31" PROC_HLASU="22.14"/>
<HLASY_STRANA KSTRANA="21" HLASY="26" PROC_HLASU="18.57"/>
<HLASY_STRANA KSTRANA="23" HLASY="7" PROC_HLASU="5.00"/>
</OBEC>
<OBEC CIS_OBEC="531146" NAZ_OBEC="Drahelčice">
<UCAST OKRSKY_CELKEM="1" OKRSKY_ZPRAC="1" OKRSKY_ZPRAC_PROC="100.00" ZAPSANI_VOLICI="468" VYDANE_OBALKY="311" UCAST_PROC="66.45" ODEVZDANE_OBALKY="311" PLATNE_HLASY="306" PLATNE_HLASY_PROC="98.39" />
<HLASY_STRANA KSTRANA="1" HLASY="42" PROC_HLASU="13.72"/>
<HLASY_STRANA KSTRANA="2" HLASY="9" PROC_HLASU="2.94"/>
<HLASY_STRANA KSTRANA="3" HLASY="3" PROC_HLASU="0.98"/>
<HLASY_STRANA KSTRANA="4" HLASY="61" PROC_HLASU="19.93"/>
<HLASY_STRANA KSTRANA="5" HLASY="3" PROC_HLASU="0.98"/>
<HLASY_STRANA KSTRANA="6" HLASY="35" PROC_HLASU="11.43"/>
<HLASY_STRANA KSTRANA="9" HLASY="2" PROC_HLASU="0.65"/>
<HLASY_STRANA KSTRANA="10" HLASY="1" PROC_HLASU="0.32"/>
<HLASY_STRANA KSTRANA="11" HLASY="6" PROC_HLASU="1.96"/>
<HLASY_STRANA KSTRANA="15" HLASY="5" PROC_HLASU="1.63"/>
<HLASY_STRANA KSTRANA="17" HLASY="11" PROC_HLASU="3.59"/>
<HLASY_STRANA KSTRANA="18" HLASY="3" PROC_HLASU="0.98"/>
<HLASY_STRANA KSTRANA="20" HLASY="67" PROC_HLASU="21.89"/>
<HLASY_STRANA KSTRANA="21" HLASY="47" PROC_HLASU="15.35"/>
<HLASY_STRANA KSTRANA="22" HLASY="1" PROC_HLASU="0.32"/>
<HLASY_STRANA KSTRANA="23" HLASY="10" PROC_HLASU="3.26"/>
</OBEC>
<OBEC CIS_OBEC="532215" NAZ_OBEC="Červený Újezd">
<UCAST OKRSKY_CELKEM="1" OKRSKY_ZPRAC="1" OKRSKY_ZPRAC_PROC="100.00" ZAPSANI_VOLICI="808" VYDANE_OBALKY="493" UCAST_PROC="61.01" ODEVZDANE_OBALKY="493" PLATNE_HLASY="489" PLATNE_HLASY_PROC="99.19" />
<HLASY_STRANA KSTRANA="1" HLASY="60" PROC_HLASU="12.26"/>
<HLASY_STRANA KSTRANA="2" HLASY="16" PROC_HLASU="3.27"/>
<HLASY_STRANA KSTRANA="3" HLASY="15" PROC_HLASU="3.06"/>
<HLASY_STRANA KSTRANA="4" HLASY="78" PROC_HLASU="15.95"/>
<HLASY_STRANA KSTRANA="5" HLASY="8" PROC_HLASU="1.63"/>
<HLASY_STRANA KSTRANA="6" HLASY="36" PROC_HLASU="7.36"/>
<HLASY_STRANA KSTRANA="9" HLASY="3" PROC_HLASU="0.61"/>
<HLASY_STRANA KSTRANA="11" HLASY="10" PROC_HLASU="2.04"/>
<HLASY_STRANA KSTRANA="13" HLASY="4" PROC_HLASU="0.81"/>
<HLASY_STRANA KSTRANA="15" HLASY="1" PROC_HLASU="0.20"/>
<HLASY_STRANA KSTRANA="17" HLASY="18" PROC_HLASU="3.68"/>
<HLASY_STRANA KSTRANA="18" HLASY="4" PROC_HLASU="0.81"/>
<HLASY_STRANA KSTRANA="20" HLASY="140" PROC_HLASU="28.62"/>
<HLASY_STRANA KSTRANA="21" HLASY="80" PROC_HLASU="16.35"/>
<HLASY_STRANA KSTRANA="23" HLASY="14" PROC_HLASU="2.86"/>
<HLASY_STRANA KSTRANA="24" HLASY="2" PROC_HLASU="0.40"/>
</OBEC>
<OBEC CIS_OBEC="539180" NAZ_OBEC="Dobříč">
<UCAST OKRSKY_CELKEM="1" OKRSKY_ZPRAC="1" OKRSKY_ZPRAC_PROC="100.00" ZAPSANI_VOLICI="234" VYDANE_OBALKY="159" UCAST_PROC="67.95" ODEVZDANE_OBALKY="159" PLATNE_HLASY="156" PLATNE_HLASY_PROC="98.11" />
<HLASY_STRANA KSTRANA="1" HLASY="25" PROC_HLASU="16.02"/>
<HLASY_STRANA KSTRANA="2" HLASY="6" PROC_HLASU="3.84"/>
<HLASY_STRANA KSTRANA="3" HLASY="7" PROC_HLASU="4.48"/>
<HLASY_STRANA KSTRANA="4" HLASY="36" PROC_HLASU="23.07"/>
<HLASY_STRANA KSTRANA="5" HLASY="1" PROC_HLASU="0.64"/>
<HLASY_STRANA KSTRANA="6" HLASY="11" PROC_HLASU="7.05"/>
<HLASY_STRANA KSTRANA="10" HLASY="1" PROC_HLASU="0.64"/>
<HLASY_STRANA KSTRANA="11" HLASY="2" PROC_HLASU="1.28"/>
<HLASY_STRANA KSTRANA="13" HLASY="1" PROC_HLASU="0.64"/>
<HLASY_STRANA KSTRANA="15" HLASY="7" PROC_HLASU="4.48"/>
<HLASY_STRANA KSTRANA="17" HLASY="6" PROC_HLASU="3.84"/>
<HLASY_STRANA KSTRANA="18" HLASY="1" PROC_HLASU="0.64"/>
<HLASY_STRANA KSTRANA="20" HLASY="34" PROC_HLASU="21.79"/>
<HLASY_STRANA KSTRANA="21" HLASY="9" PROC_HLASU="5.76"/>
<HLASY_STRANA KSTRANA="23" HLASY="8" PROC_HLASU="5.12"/>
<HLASY_STRANA KSTRANA="24" HLASY="1" PROC_HLASU="0.64"/>
</OBEC>
<OBEC CIS_OBEC="539384" NAZ_OBEC="Kněževes">
<UCAST OKRSKY_CELKEM="1" OKRSKY_ZPRAC="1" OKRSKY_ZPRAC_PROC="100.00" ZAPSANI_VOLICI="429" VYDANE_OBALKY="311" UCAST_PROC="72.49" ODEVZDANE_OBALKY="311" PLATNE_HLASY="303" PLATNE_HLASY_PROC="97.43" />
<HLASY_STRANA KSTRANA="1" HLASY="45" PROC_HLASU="14.85"/>
<HLASY_STRANA KSTRANA="2" HLASY="11" PROC_HLASU="3.63"/>
<HLASY_STRANA KSTRANA="3" HLASY="12" PROC_HLASU="3.96"/>
<HLASY_STRANA KSTRANA="4" HLASY="53" PROC_HLASU="17.49"/>
<HLASY_STRANA KSTRANA="5" HLASY="1" PROC_HLASU="0.33"/>
<HLASY_STRANA KSTRANA="6" HLASY="26" PROC_HLASU="8.58"/>
<HLASY_STRANA KSTRANA="10" HLASY="1" PROC_HLASU="0.33"/>
<HLASY_STRANA KSTRANA="11" HLASY="13" PROC_HLASU="4.29"/>
<HLASY_STRANA KSTRANA="14" HLASY="1" PROC_HLASU="0.33"/>
<HLASY_STRANA KSTRANA="15" HLASY="2" PROC_HLASU="0.66"/>
<HLASY_STRANA KSTRANA="17" HLASY="9" PROC_HLASU="2.97"/>
<HLASY_STRANA KSTRANA="18" HLASY="3" PROC_HLASU="0.99"/>
<HLASY_STRANA KSTRANA="20" HLASY="69" PROC_HLASU="22.77"/>
<HLASY_STRANA KSTRANA="21" HLASY="37" PROC_HLASU="12.21"/>
<HLASY_STRANA KSTRANA="23" HLASY="19" PROC_HLASU="6.27"/>
<HLASY_STRANA KSTRANA="24" HLASY="1" PROC_HLASU="0.33"/>
</OBEC>
<OBEC CIS_OBEC="539406" NAZ_OBEC="Lety">
<UCAST OKRSKY_CELKEM="1" OKRSKY_ZPRAC="1" OKRSKY_ZPRAC_PROC="100.00" ZAPSANI_VOLICI="1023" VYDANE_OBALKY="749" UCAST_PROC="73.22" ODEVZDANE_OBALKY="749" PLATNE_HLASY="742" PLATNE_HLASY_PROC="99.07" />
<HLASY_STRANA KSTRANA="1" HLASY="74" PROC_HLASU="9.97"/>
<HLASY_STRANA KSTRANA="2" HLASY="17" PROC_HLASU="2.29"/>
<HLASY_STRANA KSTRANA="3" HLASY="27" PROC_HLASU="3.63"/>
<HLASY_STRANA KSTRANA="4" HLASY="187" PROC_HLASU="25.20"/>
<HLASY_STRANA KSTRANA="5" HLASY="7" PROC_HLASU="0.94"/>
<HLASY_STRANA KSTRANA="6" HLASY="112" PROC_HLASU="15.09"/>
<HLASY_STRANA KSTRANA="9" HLASY="4" PROC_HLASU="0.53"/>
<HLASY_STRANA KSTRANA="11" HLASY="42" PROC_HLASU="5.66"/>
<HLASY_STRANA KSTRANA="13" HLASY="2" PROC_HLASU="0.26"/>
<HLASY_STRANA KSTRANA="15" HLASY="1" PROC_HLASU="0.13"/>
<HLASY_STRANA KSTRANA="17" HLASY="48" PROC_HLASU="6.46"/>
<HLASY_STRANA KSTRANA="18" HLASY="2" PROC_HLASU="0.26"/>
<HLASY_STRANA KSTRANA="20" HLASY="153" PROC_HLASU="20.61"/>
<HLASY_STRANA KSTRANA="21" HLASY="25" PROC_HLASU="3.36"/>
<HLASY_STRANA KSTRANA="23" HLASY="41" PROC_HLASU="5.52"/>
</OBEC>
<OBEC CIS_OBEC="539571" NAZ_OBEC="Průhonice">
<UCAST OKRSKY_CELKEM="1" OKRSKY_ZPRAC="1" OKRSKY_ZPRAC_PROC="100.00" ZAPSANI_VOLICI="1744" VYDANE_OBALKY="1298" UCAST_PROC="74.43" ODEVZDANE_OBALKY="1293" PLATNE_HLASY="1279" PLATNE_HLASY_PROC="98.92" />
<HLASY_STRANA KSTRANA="1" HLASY="113" PROC_HLASU="8.83"/>
<HLASY_STRANA KSTRANA="2" HLASY="43" PROC_HLASU="3.36"/>
<HLASY_STRANA KSTRANA="3" HLASY="18" PROC_HLASU="1.40"/>
<HLASY_STRANA KSTRANA="4" HLASY="289" PROC_HLASU="22.59"/>
<HLASY_STRANA KSTRANA="5" HLASY="3" PROC_HLASU="0.23"/>
<HLASY_STRANA KSTRANA="6" HLASY="154" PROC_HLASU="12.04"/>
<HLASY_STRANA KSTRANA="9" HLASY="4" PROC_HLASU="0.31"/>
<HLASY_STRANA KSTRANA="10" HLASY="3" PROC_HLASU="0.23"/>
<HLASY_STRANA KSTRANA="11" HLASY="64" PROC_HLASU="5.00"/>
<HLASY_STRANA KSTRANA="14" HLASY="3" PROC_HLASU="0.23"/>
<HLASY_STRANA KSTRANA="15" HLASY="10" PROC_HLASU="0.78"/>
<HLASY_STRANA KSTRANA="17" HLASY="43" PROC_HLASU="3.36"/>
<HLASY_STRANA KSTRANA="18" HLASY="5" PROC_HLASU="0.39"/>
<HLASY_STRANA KSTRANA="20" HLASY="398" PROC_HLASU="31.11"/>
<HLASY_STRANA KSTRANA="21" HLASY="75" PROC_HLASU="5.86"/>
<HLASY_STRANA KSTRANA="23" HLASY="51" PROC_HLASU="3.98"/>
<HLASY_STRANA KSTRANA="24" HLASY="3" PROC_HLASU="0.23"/>
</OBEC>
<OBEC CIS_OBEC="539686" NAZ_OBEC="Statenice">
<UCAST OKRSKY_CELKEM="1" OKRSKY_ZPRAC="1" OKRSKY_ZPRAC_PROC="100.00" ZAPSANI_VOLICI="911" VYDANE_OBALKY="627" UCAST_PROC="68.83" ODEVZDANE_OBALKY="627" PLATNE_HLASY="623" PLATNE_HLASY_PROC="99.36" />
<HLASY_STRANA KSTRANA="1" HLASY="69" PROC_HLASU="11.07"/>
<HLASY_STRANA KSTRANA="2" HLASY="27" PROC_HLASU="4.33"/>
<HLASY_STRANA KSTRANA="3" HLASY="14" PROC_HLASU="2.24"/>
<HLASY_STRANA KSTRANA="4" HLASY="177" PROC_HLASU="28.41"/>
<HLASY_STRANA KSTRANA="5" HLASY="3" PROC_HLASU="0.48"/>
<HLASY_STRANA KSTRANA="6" HLASY="73" PROC_HLASU="11.71"/>
<HLASY_STRANA KSTRANA="9" HLASY="2" PROC_HLASU="0.32"/>
<HLASY_STRANA KSTRANA="10" HLASY="2" PROC_HLASU="0.32"/>
<HLASY_STRANA KSTRANA="11" HLASY="33" PROC_HLASU="5.29"/>
<HLASY_STRANA KSTRANA="15" HLASY="6" PROC_HLASU="0.96"/>
<HLASY_STRANA KSTRANA="17" HLASY="18" PROC_HLASU="2.88"/>
<HLASY_STRANA KSTRANA="18" HLASY="4" PROC_HLASU="0.64"/>
<HLASY_STRANA KSTRANA="20" HLASY="127" PROC_HLASU="20.38"/>
<HLASY_STRANA KSTRANA="21" HLASY="35" PROC_HLASU="5.61"/>
<HLASY_STRANA KSTRANA="23" HLASY="31" PROC_HLASU="4.97"/>
<HLASY_STRANA KSTRANA="24" HLASY="2" PROC_HLASU="0.32"/>
</OBEC>
<OBEC CIS_OBEC="571288" NAZ_OBEC="Zahořany">
<UCAST OKRSKY_CELKEM="1" OKRSKY_ZPRAC="1" OKRSKY_ZPRAC_PROC="100.00" ZAPSANI_VOLICI="219" VYDANE_OBALKY="161" UCAST_PROC="73.52" ODEVZDANE_OBALKY="161" PLATNE_HLASY="160" PLATNE_HLASY_PROC="99.38" />
<HLASY_STRANA KSTRANA="1" HLASY="18" PROC_HLASU="11.25"/>
<HLASY_STRANA KSTRANA="2" HLASY="6" PROC_HLASU="3.75"/>
<HLASY_STRANA KSTRANA="3" HLASY="5" PROC_HLASU="3.12"/>
<HLASY_STRANA KSTRANA="4" HLASY="33" PROC_HLASU="20.62"/>
<HLASY_STRANA KSTRANA="5" HLASY="1" PROC_HLASU="0.62"/>
<HLASY_STRANA KSTRANA="6" HLASY="17" PROC_HLASU="10.62"/>
<HLASY_STRANA KSTRANA="11" HLASY="12" PROC_HLASU="7.50"/>
<HLASY_STRANA KSTRANA="13" HLASY="1" PROC_HLASU="0.62"/>
<HLASY_STRANA KSTRANA="14" HLASY="1" PROC_HLASU="0.62"/>
<HLASY_STRANA KSTRANA="15" HLASY="2" PROC_HLASU="1.25"/>
<HLASY_STRANA KSTRANA="17" HLASY="1" PROC_HLASU="0.62"/>
<HLASY_STRANA KSTRANA="20" HLASY="33" PROC_HLASU="20.62"/>
<HLASY_STRANA KSTRANA="21" HLASY="20" PROC_HLASU="12.50"/>
<HLASY_STRANA KSTRANA="23" HLASY="10" PROC_HLASU="6.25"/>
</OBEC>
<OBEC CIS_OBEC="513431" NAZ_OBEC="Chýnice">
<UCAST OKRSKY_CELKEM="1" OKRSKY_ZPRAC="1" OKRSKY_ZPRAC_PROC="100.00" ZAPSANI_VOLICI="280" VYDANE_OBALKY="207" UCAST_PROC="73.93" ODEVZDANE_OBALKY="207" PLATNE_HLASY="205" PLATNE_HLASY_PROC="99.03" />
<HLASY_STRANA KSTRANA="1" HLASY="29" PROC_HLASU="14.14"/>
<HLASY_STRANA KSTRANA="2" HLASY="9" PROC_HLASU="4.39"/>
<HLASY_STRANA KSTRANA="3" HLASY="9" PROC_HLASU="4.39"/>
<HLASY_STRANA KSTRANA="4" HLASY="53" PROC_HLASU="25.85"/>
<HLASY_STRANA KSTRANA="5" HLASY="3" PROC_HLASU="1.46"/>
<HLASY_STRANA KSTRANA="6" HLASY="28" PROC_HLASU="13.65"/>
<HLASY_STRANA KSTRANA="10" HLASY="1" PROC_HLASU="0.48"/>
<HLASY_STRANA KSTRANA="11" HLASY="7" PROC_HLASU="3.41"/>
<HLASY_STRANA KSTRANA="15" HLASY="3" PROC_HLASU="1.46"/>
<HLASY_STRANA KSTRANA="17" HLASY="9" PROC_HLASU="4.39"/>
<HLASY_STRANA KSTRANA="20" HLASY="33" PROC_HLASU="16.09"/>
<HLASY_STRANA KSTRANA="21" HLASY="13" PROC_HLASU="6.34"/>
<HLASY_STRANA KSTRANA="23" HLASY="8" PROC_HLASU="3.90"/>
</OBEC>
<OBEC CIS_OBEC="531618" NAZ_OBEC="Nučice">
<UCAST OKRSKY_CELKEM="1" OKRSKY_ZPRAC="1" OKRSKY_ZPRAC_PROC="100.00" ZAPSANI_VOLICI="1425" VYDANE_OBALKY="973" UCAST_PROC="68.28" ODEVZDANE_OBALKY="973" PLATNE_HLASY="962" PLATNE_HLASY_PROC="98.87" />
<HLASY_STRANA KSTRANA="1" HLASY="104" PROC_HLASU="10.81"/>
<HLASY_STRANA KSTRANA="2" HLASY="44" PROC_HLASU="4.57"/>
<HLASY_STRANA KSTRANA="3" HLASY="33" PROC_HLASU="3.43"/>
<HLASY_STRANA KSTRANA="4" HLASY="249" PROC_HLASU="25.88"/>
<HLASY_STRANA KSTRANA="5" HLASY="8" PROC_HLASU="0.83"/>
<HLASY_STRANA KSTRANA="6" HLASY="105" PROC_HLASU="10.91"/>
<HLASY_STRANA KSTRANA="9" HLASY="4" PROC_HLASU="0.41"/>
<HLASY_STRANA KSTRANA="10" HLASY="4" PROC_HLASU="0.41"/>
<HLASY_STRANA KSTRANA="11" HLASY="38" PROC_HLASU="3.95"/>
<HLASY_STRANA KSTRANA="13" HLASY="1" PROC_HLASU="0.10"/>
<HLASY_STRANA KSTRANA="15" HLASY="6" PROC_HLASU="0.62"/>
<HLASY_STRANA KSTRANA="17" HLASY="51" PROC_HLASU="5.30"/>
<HLASY_STRANA KSTRANA="18" HLASY="6" PROC_HLASU="0.62"/>
<HLASY_STRANA KSTRANA="20" HLASY="181" PROC_HLASU="18.81"/>
<HLASY_STRANA KSTRANA="21" HLASY="59" PROC_HLASU="6.13"/>
<HLASY_STRANA KSTRANA="23" HLASY="69" PROC_HLASU="7.17"/>
</OBEC>
<OBEC CIS_OBEC="539333" NAZ_OBEC="Jílové u Prahy">
<UCAST OKRSKY_CELKEM="6" OKRSKY_ZPRAC="6" OKRSKY_ZPRAC_PROC="100.00" ZAPSANI_VOLICI="3418" VYDANE_OBALKY="2156" UCAST_PROC="63.08" ODEVZDANE_OBALKY="2155" PLATNE_HLASY="2131" PLATNE_HLASY_PROC="98.89" />
<HLASY_STRANA KSTRANA="1" HLASY="266" PROC_HLASU="12.48"/>
<HLASY_STRANA KSTRANA="2" HLASY="53" PROC_HLASU="2.48"/>
<HLASY_STRANA KSTRANA="3" HLASY="78" PROC_HLASU="3.66"/>
<HLASY_STRANA KSTRANA="4" HLASY="416" PROC_HLASU="19.52"/>
<HLASY_STRANA KSTRANA="5" HLASY="17" PROC_HLASU="0.79"/>
<HLASY_STRANA KSTRANA="6" HLASY="190" PROC_HLASU="8.91"/>
<HLASY_STRANA KSTRANA="9" HLASY="14" PROC_HLASU="0.65"/>
<HLASY_STRANA KSTRANA="10" HLASY="6" PROC_HLASU="0.28"/>
<HLASY_STRANA KSTRANA="11" HLASY="74" PROC_HLASU="3.47"/>
<HLASY_STRANA KSTRANA="13" HLASY="12" PROC_HLASU="0.56"/>
<HLASY_STRANA KSTRANA="14" HLASY="2" PROC_HLASU="0.09"/>
<HLASY_STRANA KSTRANA="15" HLASY="48" PROC_HLASU="2.25"/>
<HLASY_STRANA KSTRANA="17" HLASY="126" PROC_HLASU="5.91"/>
<HLASY_STRANA KSTRANA="18" HLASY="14" PROC_HLASU="0.65"/>
<HLASY_STRANA KSTRANA="20" HLASY="438" PROC_HLASU="20.55"/>
<HLASY_STRANA KSTRANA="21" HLASY="244" PROC_HLASU="11.45"/>
<HLASY_STRANA KSTRANA="22" HLASY="3" PROC_HLASU="0.14"/>
<HLASY_STRANA KSTRANA="23" HLASY="119" PROC_HLASU="5.58"/>
<HLASY_STRANA KSTRANA="24" HLASY="11" PROC_HLASU="0.51"/>
</OBEC>
<OBEC CIS_OBEC="539392" NAZ_OBEC="Kosoř">
<UCAST OKRSKY_CELKEM="1" OKRSKY_ZPRAC="1" OKRSKY_ZPRAC_PROC="100.00" ZAPSANI_VOLICI="673" VYDANE_OBALKY="422" UCAST_PROC="62.70" ODEVZDANE_OBALKY="422" PLATNE_HLASY="420" PLATNE_HLASY_PROC="99.53" />
<HLASY_STRANA KSTRANA="1" HLASY="62" PROC_HLASU="14.76"/>
<HLASY_STRANA KSTRANA="2" HLASY="13" PROC_HLASU="3.09"/>
<HLASY_STRANA KSTRANA="3" HLASY="10" PROC_HLASU="2.38"/>
<HLASY_STRANA KSTRANA="4" HLASY="87" PROC_HLASU="20.71"/>
<HLASY_STRANA KSTRANA="5" HLASY="5" PROC_HLASU="1.19"/>
<HLASY_STRANA KSTRANA="6" HLASY="49" PROC_HLASU="11.66"/>
<HLASY_STRANA KSTRANA="9" HLASY="6" PROC_HLASU="1.42"/>
<HLASY_STRANA KSTRANA="10" HLASY="2" PROC_HLASU="0.47"/>
<HLASY_STRANA KSTRANA="11" HLASY="16" PROC_HLASU="3.80"/>
<HLASY_STRANA KSTRANA="13" HLASY="1" PROC_HLASU="0.23"/>
<HLASY_STRANA KSTRANA="15" HLASY="3" PROC_HLASU="0.71"/>
<HLASY_STRANA KSTRANA="17" HLASY="23" PROC_HLASU="5.47"/>
<HLASY_STRANA KSTRANA="18" HLASY="1" PROC_HLASU="0.23"/>
<HLASY_STRANA KSTRANA="20" HLASY="69" PROC_HLASU="16.42"/>
<HLASY_STRANA KSTRANA="21" HLASY="52" PROC_HLASU="12.38"/>
<HLASY_STRANA KSTRANA="23" HLASY="21" PROC_HLASU="5.00"/>
</OBEC>
<OBEC CIS_OBEC="539457" NAZ_OBEC="Líšnice">
<UCAST OKRSKY_CELKEM="1" OKRSKY_ZPRAC="1" OKRSKY_ZPRAC_PROC="100.00" ZAPSANI_VOLICI="480" VYDANE_OBALKY="337" UCAST_PROC="70.21" ODEVZDANE_OBALKY="337" PLATNE_HLASY="337" PLATNE_HLASY_PROC="100.00" />
<HLASY_STRANA KSTRANA="1" HLASY="38" PROC_HLASU="11.27"/>
<HLASY_STRANA KSTRANA="2" HLASY="6" PROC_HLASU="1.78"/>
<HLASY_STRANA KSTRANA="3" HLASY="15" PROC_HLASU="4.45"/>
<HLASY_STRANA KSTRANA="4" HLASY="100" PROC_HLASU="29.67"/>
<HLASY_STRANA KSTRANA="5" HLASY="4" PROC_HLASU="1.18"/>
<HLASY_STRANA KSTRANA="6" HLASY="34" PROC_HLASU="10.08"/>
<HLASY_STRANA KSTRANA="11" HLASY="13" PROC_HLASU="3.85"/>
<HLASY_STRANA KSTRANA="15" HLASY="2" PROC_HLASU="0.59"/>
<HLASY_STRANA KSTRANA="17" HLASY="17" PROC_HLASU="5.04"/>
<HLASY_STRANA KSTRANA="20" HLASY="66" PROC_HLASU="19.58"/>
<HLASY_STRANA KSTRANA="21" HLASY="26" PROC_HLASU="7.71"/>
<HLASY_STRANA KSTRANA="23" HLASY="16" PROC_HLASU="4.74"/>
</OBEC>
<OBEC CIS_OBEC="539490" NAZ_OBEC="Měchenice">
<UCAST OKRSKY_CELKEM="1" OKRSKY_ZPRAC="1" OKRSKY_ZPRAC_PROC="100.00" ZAPSANI_VOLICI="603" VYDANE_OBALKY="415" UCAST_PROC="68.82" ODEVZDANE_OBALKY="414" PLATNE_HLASY="408" PLATNE_HLASY_PROC="98.55" />
<HLASY_STRANA KSTRANA="1" HLASY="51" PROC_HLASU="12.50"/>
<HLASY_STRANA KSTRANA="2" HLASY="20" PROC_HLASU="4.90"/>
<HLASY_STRANA KSTRANA="3" HLASY="4" PROC_HLASU="0.98"/>
<HLASY_STRANA KSTRANA="4" HLASY="110" PROC_HLASU="26.96"/>
<HLASY_STRANA KSTRANA="5" HLASY="1" PROC_HLASU="0.24"/>
<HLASY_STRANA KSTRANA="6" HLASY="40" PROC_HLASU="9.80"/>
<HLASY_STRANA KSTRANA="11" HLASY="21" PROC_HLASU="5.14"/>
<HLASY_STRANA KSTRANA="15" HLASY="5" PROC_HLASU="1.22"/>
<HLASY_STRANA KSTRANA="17" HLASY="22" PROC_HLASU="5.39"/>
<HLASY_STRANA KSTRANA="20" HLASY="86" PROC_HLASU="21.07"/>
<HLASY_STRANA KSTRANA="21" HLASY="32" PROC_HLASU="7.84"/>
<HLASY_STRANA KSTRANA="23" HLASY="14" PROC_HLASU="3.43"/>
<HLASY_STRANA KSTRANA="24" HLASY="2" PROC_HLASU="0.49"/>
</OBEC>
<OBEC CIS_OBEC="539708" NAZ_OBEC="Středokluky">
<UCAST OKRSKY_CELKEM="1" OKRSKY_ZPRAC="1" OKRSKY_ZPRAC_PROC="100.00" ZAPSANI_VOLICI="801" VYDANE_OBALKY="548" UCAST_PROC="68.41" ODEVZDANE_OBALKY="548" PLATNE_HLASY="544" PLATNE_HLASY_PROC="99.27" />
<HLASY_STRANA KSTRANA="1" HLASY="62" PROC_HLASU="11.39"/>
<HLASY_STRANA KSTRANA="2" HLASY="15" PROC_HLASU="2.75"/>
<HLASY_STRANA KSTRANA="3" HLASY="18" PROC_HLASU="3.30"/>
<HLASY_STRANA KSTRANA="4" HLASY="117" PROC_HLASU="21.50"/>
<HLASY_STRANA KSTRANA="5" HLASY="1" PROC_HLASU="0.18"/>
<HLASY_STRANA KSTRANA="6" HLASY="58" PROC_HLASU="10.66"/>
<HLASY_STRANA KSTRANA="7" HLASY="1" PROC_HLASU="0.18"/>
<HLASY_STRANA KSTRANA="9" HLASY="4" PROC_HLASU="0.73"/>
<HLASY_STRANA KSTRANA="10" HLASY="1" PROC_HLASU="0.18"/>
<HLASY_STRANA KSTRANA="11" HLASY="17" PROC_HLASU="3.12"/>
<HLASY_STRANA KSTRANA="15" HLASY="10" PROC_HLASU="1.83"/>
<HLASY_STRANA KSTRANA="17" HLASY="29" PROC_HLASU="5.33"/>
<HLASY_STRANA KSTRANA="18" HLASY="4" PROC_HLASU="0.73"/>
<HLASY_STRANA KSTRANA="20" HLASY="108" PROC_HLASU="19.85"/>
<HLASY_STRANA KSTRANA="21" HLASY="73" PROC_HLASU="13.41"/>
<HLASY_STRANA KSTRANA="22" HLASY="1" PROC_HLASU="0.18"/>
<HLASY_STRANA KSTRANA="23" HLASY="25" PROC_HLASU="4.59"/>
</OBEC>
<OBEC CIS_OBEC="539775" NAZ_OBEC="Tursko">
<UCAST OKRSKY_CELKEM="1" OKRSKY_ZPRAC="1" OKRSKY_ZPRAC_PROC="100.00" ZAPSANI_VOLICI="556" VYDANE_OBALKY="352" UCAST_PROC="63.31" ODEVZDANE_OBALKY="352" PLATNE_HLASY="350" PLATNE_HLASY_PROC="99.43" />
<HLASY_STRANA KSTRANA="1" HLASY="46" PROC_HLASU="13.14"/>
<HLASY_STRANA KSTRANA="2" HLASY="16" PROC_HLASU="4.57"/>
<HLASY_STRANA KSTRANA="3" HLASY="9" PROC_HLASU="2.57"/>
<HLASY_STRANA KSTRANA="4" HLASY="66" PROC_HLASU="18.85"/>
<HLASY_STRANA KSTRANA="5" HLASY="1" PROC_HLASU="0.28"/>
<HLASY_STRANA KSTRANA="6" HLASY="35" PROC_HLASU="10.00"/>
<HLASY_STRANA KSTRANA="7" HLASY="1" PROC_HLASU="0.28"/>
<HLASY_STRANA KSTRANA="10" HLASY="2" PROC_HLASU="0.57"/>
<HLASY_STRANA KSTRANA="11" HLASY="18" PROC_HLASU="5.14"/>
<HLASY_STRANA KSTRANA="13" HLASY="1" PROC_HLASU="0.28"/>
<HLASY_STRANA KSTRANA="15" HLASY="2" PROC_HLASU="0.57"/>
<HLASY_STRANA KSTRANA="17" HLASY="24" PROC_HLASU="6.85"/>
<HLASY_STRANA KSTRANA="18" HLASY="4" PROC_HLASU="1.14"/>
<HLASY_STRANA KSTRANA="20" HLASY="60" PROC_HLASU="17.14"/>
<HLASY_STRANA KSTRANA="21" HLASY="49" PROC_HLASU="14.00"/>
<HLASY_STRANA KSTRANA="23" HLASY="16" PROC_HLASU="4.57"/>
</OBEC>
<OBEC CIS_OBEC="540048" NAZ_OBEC="Buš">
<UCAST OKRSKY_CELKEM="1" OKRSKY_ZPRAC="1" OKRSKY_ZPRAC_PROC="100.00" ZAPSANI_VOLICI="278" VYDANE_OBALKY="188" UCAST_PROC="67.63" ODEVZDANE_OBALKY="188" PLATNE_HLASY="187" PLATNE_HLASY_PROC="99.47" />
<HLASY_STRANA KSTRANA="1" HLASY="17" PROC_HLASU="9.09"/>
<HLASY_STRANA KSTRANA="2" HLASY="1" PROC_HLASU="0.53"/>
<HLASY_STRANA KSTRANA="3" HLASY="3" PROC_HLASU="1.60"/>
<HLASY_STRANA KSTRANA="4" HLASY="35" PROC_HLASU="18.71"/>
<HLASY_STRANA KSTRANA="5" HLASY="2" PROC_HLASU="1.06"/>
<HLASY_STRANA KSTRANA="6" HLASY="28" PROC_HLASU="14.97"/>
<HLASY_STRANA KSTRANA="11" HLASY="21" PROC_HLASU="11.22"/>
<HLASY_STRANA KSTRANA="15" HLASY="1" PROC_HLASU="0.53"/>
<HLASY_STRANA KSTRANA="17" HLASY="9" PROC_HLASU="4.81"/>
<HLASY_STRANA KSTRANA="18" HLASY="3" PROC_HLASU="1.60"/>
<HLASY_STRANA KSTRANA="20" HLASY="38" PROC_HLASU="20.32"/>
<HLASY_STRANA KSTRANA="21" HLASY="22" PROC_HLASU="11.76"/>
<HLASY_STRANA KSTRANA="23" HLASY="7" PROC_HLASU="3.74"/>
</OBEC>
<OBEC CIS_OBEC="571318" NAZ_OBEC="Roblín">
<UCAST OKRSKY_CELKEM="1" OKRSKY_ZPRAC="1" OKRSKY_ZPRAC_PROC="100.00" ZAPSANI_VOLICI="172" VYDANE_OBALKY="114" UCAST_PROC="66.28" ODEVZDANE_OBALKY="114" PLATNE_HLASY="114" PLATNE_HLASY_PROC="100.00" />
<HLASY_STRANA KSTRANA="1" HLASY="17" PROC_HLASU="14.91"/>
<HLASY_STRANA KSTRANA="3" HLASY="4" PROC_HLASU="3.50"/>
<HLASY_STRANA KSTRANA="4" HLASY="24" PROC_HLASU="21.05"/>
<HLASY_STRANA KSTRANA="5" HLASY="1" PROC_HLASU="0.87"/>
<HLASY_STRANA KSTRANA="6" HLASY="18" PROC_HLASU="15.78"/>
<HLASY_STRANA KSTRANA="10" HLASY="1" PROC_HLASU="0.87"/>
<HLASY_STRANA KSTRANA="17" HLASY="2" PROC_HLASU="1.75"/>
<HLASY_STRANA KSTRANA="20" HLASY="27" PROC_HLASU="23.68"/>
<HLASY_STRANA KSTRANA="21" HLASY="17" PROC_HLASU="14.91"/>
<HLASY_STRANA KSTRANA="23" HLASY="3" PROC_HLASU="2.63"/>
</OBEC>
<OBEC CIS_OBEC="599735" NAZ_OBEC="Březová-Oleško">
<UCAST OKRSKY_CELKEM="1" OKRSKY_ZPRAC="1" OKRSKY_ZPRAC_PROC="100.00" ZAPSANI_VOLICI="746" VYDANE_OBALKY="515" UCAST_PROC="69.03" ODEVZDANE_OBALKY="515" PLATNE_HLASY="507" PLATNE_HLASY_PROC="98.45" />
<HLASY_STRANA KSTRANA="1" HLASY="49" PROC_HLASU="9.66"/>
<HLASY_STRANA KSTRANA="2" HLASY="13" PROC_HLASU="2.56"/>
<HLASY_STRANA KSTRANA="3" HLASY="11" PROC_HLASU="2.16"/>
<HLASY_STRANA KSTRANA="4" HLASY="129" PROC_HLASU="25.44"/>
<HLASY_STRANA KSTRANA="5" HLASY="5" PROC_HLASU="0.98"/>
<HLASY_STRANA KSTRANA="6" HLASY="36" PROC_HLASU="7.10"/>
<HLASY_STRANA KSTRANA="7" HLASY="2" PROC_HLASU="0.39"/>
<HLASY_STRANA KSTRANA="9" HLASY="2" PROC_HLASU="0.39"/>
<HLASY_STRANA KSTRANA="10" HLASY="5" PROC_HLASU="0.98"/>
<HLASY_STRANA KSTRANA="11" HLASY="7" PROC_HLASU="1.38"/>
<HLASY_STRANA KSTRANA="13" HLASY="1" PROC_HLASU="0.19"/>
<HLASY_STRANA KSTRANA="14" HLASY="1" PROC_HLASU="0.19"/>
<HLASY_STRANA KSTRANA="15" HLASY="4" PROC_HLASU="0.78"/>
<HLASY_STRANA KSTRANA="17" HLASY="29" PROC_HLASU="5.71"/>
<HLASY_STRANA KSTRANA="18" HLASY="1" PROC_HLASU="0.19"/>
<HLASY_STRANA KSTRANA="20" HLASY="146" PROC_HLASU="28.79"/>
<HLASY_STRANA KSTRANA="21" HLASY="49" PROC_HLASU="9.66"/>
<HLASY_STRANA KSTRANA="22" HLASY="1" PROC_HLASU="0.19"/>
<HLASY_STRANA KSTRANA="23" HLASY="15" PROC_HLASU="2.95"/>
<HLASY_STRANA KSTRANA="24" HLASY="1" PROC_HLASU="0.19"/>
</OBEC>
<OBEC CIS_OBEC="532789" NAZ_OBEC="Ptice">
<UCAST OKRSKY_CELKEM="1" OKRSKY_ZPRAC="1" OKRSKY_ZPRAC_PROC="100.00" ZAPSANI_VOLICI="546" VYDANE_OBALKY="406" UCAST_PROC="74.36" ODEVZDANE_OBALKY="405" PLATNE_HLASY="403" PLATNE_HLASY_PROC="99.51" />
<HLASY_STRANA KSTRANA="1" HLASY="54" PROC_HLASU="13.39"/>
<HLASY_STRANA KSTRANA="2" HLASY="9" PROC_HLASU="2.23"/>
<HLASY_STRANA KSTRANA="3" HLASY="17" PROC_HLASU="4.21"/>
<HLASY_STRANA KSTRANA="4" HLASY="91" PROC_HLASU="22.58"/>
<HLASY_STRANA KSTRANA="5" HLASY="6" PROC_HLASU="1.48"/>
<HLASY_STRANA KSTRANA="6" HLASY="51" PROC_HLASU="12.65"/>
<HLASY_STRANA KSTRANA="7" HLASY="1" PROC_HLASU="0.24"/>
<HLASY_STRANA KSTRANA="9" HLASY="3" PROC_HLASU="0.74"/>
<HLASY_STRANA KSTRANA="10" HLASY="1" PROC_HLASU="0.24"/>
<HLASY_STRANA KSTRANA="11" HLASY="16" PROC_HLASU="3.97"/>
<HLASY_STRANA KSTRANA="13" HLASY="1" PROC_HLASU="0.24"/>
<HLASY_STRANA KSTRANA="14" HLASY="1" PROC_HLASU="0.24"/>
<HLASY_STRANA KSTRANA="15" HLASY="1" PROC_HLASU="0.24"/>
<HLASY_STRANA KSTRANA="17" HLASY="12" PROC_HLASU="2.97"/>
<HLASY_STRANA KSTRANA="18" HLASY="1" PROC_HLASU="0.24"/>
<HLASY_STRANA KSTRANA="20" HLASY="83" PROC_HLASU="20.59"/>
<HLASY_STRANA KSTRANA="21" HLASY="39" PROC_HLASU="9.67"/>
<HLASY_STRANA KSTRANA="23" HLASY="16" PROC_HLASU="3.97"/>
</OBEC>
<OBEC CIS_OBEC="539139" NAZ_OBEC="Černošice">
<UCAST OKRSKY_CELKEM="5" OKRSKY_ZPRAC="5" OKRSKY_ZPRAC_PROC="100.00" ZAPSANI_VOLICI="4929" VYDANE_OBALKY="3711" UCAST_PROC="75.29" ODEVZDANE_OBALKY="3711" PLATNE_HLASY="3684" PLATNE_HLASY_PROC="99.27" />
<HLASY_STRANA KSTRANA="1" HLASY="334" PROC_HLASU="9.06"/>
<HLASY_STRANA KSTRANA="2" HLASY="135" PROC_HLASU="3.66"/>
<HLASY_STRANA KSTRANA="3" HLASY="114" PROC_HLASU="3.09"/>
<HLASY_STRANA KSTRANA="4" HLASY="1209" PROC_HLASU="32.81"/>
<HLASY_STRANA KSTRANA="5" HLASY="14" PROC_HLASU="0.38"/>
<HLASY_STRANA KSTRANA="6" HLASY="481" PROC_HLASU="13.05"/>
<HLASY_STRANA KSTRANA="7" HLASY="3" PROC_HLASU="0.08"/>
<HLASY_STRANA KSTRANA="9" HLASY="39" PROC_HLASU="1.05"/>
<HLASY_STRANA KSTRANA="10" HLASY="9" PROC_HLASU="0.24"/>
<HLASY_STRANA KSTRANA="11" HLASY="208" PROC_HLASU="5.64"/>
<HLASY_STRANA KSTRANA="13" HLASY="4" PROC_HLASU="0.10"/>
<HLASY_STRANA KSTRANA="14" HLASY="1" PROC_HLASU="0.02"/>
<HLASY_STRANA KSTRANA="15" HLASY="31" PROC_HLASU="0.84"/>
<HLASY_STRANA KSTRANA="17" HLASY="118" PROC_HLASU="3.20"/>
<HLASY_STRANA KSTRANA="18" HLASY="9" PROC_HLASU="0.24"/>
<HLASY_STRANA KSTRANA="20" HLASY="492" PROC_HLASU="13.35"/>
<HLASY_STRANA KSTRANA="21" HLASY="211" PROC_HLASU="5.72"/>
<HLASY_STRANA KSTRANA="22" HLASY="1" PROC_HLASU="0.02"/>
<HLASY_STRANA KSTRANA="23" HLASY="267" PROC_HLASU="7.24"/>
<HLASY_STRANA KSTRANA="24" HLASY="4" PROC_HLASU="0.10"/>
</OBEC>
<OBEC CIS_OBEC="539147" NAZ_OBEC="Číčovice">
<UCAST OKRSKY_CELKEM="1" OKRSKY_ZPRAC="1" OKRSKY_ZPRAC_PROC="100.00" ZAPSANI_VOLICI="225" VYDANE_OBALKY="150" UCAST_PROC="66.67" ODEVZDANE_OBALKY="150" PLATNE_HLASY="149" PLATNE_HLASY_PROC="99.33" />
<HLASY_STRANA KSTRANA="1" HLASY="17" PROC_HLASU="11.40"/>
<HLASY_STRANA KSTRANA="2" HLASY="3" PROC_HLASU="2.01"/>
<HLASY_STRANA KSTRANA="3" HLASY="6" PROC_HLASU="4.02"/>
<HLASY_STRANA KSTRANA="4" HLASY="31" PROC_HLASU="20.80"/>
<HLASY_STRANA KSTRANA="6" HLASY="11" PROC_HLASU="7.38"/>
<HLASY_STRANA KSTRANA="9" HLASY="2" PROC_HLASU="1.34"/>
<HLASY_STRANA KSTRANA="10" HLASY="3" PROC_HLASU="2.01"/>
<HLASY_STRANA KSTRANA="11" HLASY="5" PROC_HLASU="3.35"/>
<HLASY_STRANA KSTRANA="17" HLASY="4" PROC_HLASU="2.68"/>
<HLASY_STRANA KSTRANA="18" HLASY="2" PROC_HLASU="1.34"/>
<HLASY_STRANA KSTRANA="20" HLASY="31" PROC_HLASU="20.80"/>
<HLASY_STRANA KSTRANA="21" HLASY="32" PROC_HLASU="21.47"/>
<HLASY_STRANA KSTRANA="23" HLASY="1" PROC_HLASU="0.67"/>
<HLASY_STRANA KSTRANA="24" HLASY="1" PROC_HLASU="0.67"/>
</OBEC>
<OBEC CIS_OBEC="539236" NAZ_OBEC="Horoměřice">
<UCAST OKRSKY_CELKEM="2" OKRSKY_ZPRAC="2" OKRSKY_ZPRAC_PROC="100.00" ZAPSANI_VOLICI="2366" VYDANE_OBALKY="1596" UCAST_PROC="67.46" ODEVZDANE_OBALKY="1596" PLATNE_HLASY="1579" PLATNE_HLASY_PROC="98.93" />
<HLASY_STRANA KSTRANA="1" HLASY="181" PROC_HLASU="11.46"/>
<HLASY_STRANA KSTRANA="2" HLASY="58" PROC_HLASU="3.67"/>
<HLASY_STRANA KSTRANA="3" HLASY="46" PROC_HLASU="2.91"/>
<HLASY_STRANA KSTRANA="4" HLASY="394" PROC_HLASU="24.95"/>
<HLASY_STRANA KSTRANA="5" HLASY="6" PROC_HLASU="0.37"/>
<HLASY_STRANA KSTRANA="6" HLASY="191" PROC_HLASU="12.09"/>
<HLASY_STRANA KSTRANA="7" HLASY="2" PROC_HLASU="0.12"/>
<HLASY_STRANA KSTRANA="9" HLASY="4" PROC_HLASU="0.25"/>
<HLASY_STRANA KSTRANA="10" HLASY="3" PROC_HLASU="0.18"/>
<HLASY_STRANA KSTRANA="11" HLASY="74" PROC_HLASU="4.68"/>
<HLASY_STRANA KSTRANA="13" HLASY="2" PROC_HLASU="0.12"/>
<HLASY_STRANA KSTRANA="15" HLASY="19" PROC_HLASU="1.20"/>
<HLASY_STRANA KSTRANA="17" HLASY="56" PROC_HLASU="3.54"/>
<HLASY_STRANA KSTRANA="18" HLASY="7" PROC_HLASU="0.44"/>
<HLASY_STRANA KSTRANA="20" HLASY="318" PROC_HLASU="20.13"/>
<HLASY_STRANA KSTRANA="21" HLASY="127" PROC_HLASU="8.04"/>
<HLASY_STRANA KSTRANA="23" HLASY="87" PROC_HLASU="5.50"/>
<HLASY_STRANA KSTRANA="24" HLASY="4" PROC_HLASU="0.25"/>
</OBEC>
<OBEC CIS_OBEC="539244" NAZ_OBEC="Hostivice">
<UCAST OKRSKY_CELKEM="5" OKRSKY_ZPRAC="5" OKRSKY_ZPRAC_PROC="100.00" ZAPSANI_VOLICI="5537" VYDANE_OBALKY="3569" UCAST_PROC="64.46" ODEVZDANE_OBALKY="3569" PLATNE_HLASY="3544" PLATNE_HLASY_PROC="99.30" />
<HLASY_STRANA KSTRANA="1" HLASY="413" PROC_HLASU="11.65"/>
<HLASY_STRANA KSTRANA="2" HLASY="139" PROC_HLASU="3.92"/>
<HLASY_STRANA KSTRANA="3" HLASY="91" PROC_HLASU="2.56"/>
<HLASY_STRANA KSTRANA="4" HLASY="874" PROC_HLASU="24.66"/>
<HLASY_STRANA KSTRANA="5" HLASY="11" PROC_HLASU="0.31"/>
<HLASY_STRANA KSTRANA="6" HLASY="355" PROC_HLASU="10.01"/>
<HLASY_STRANA KSTRANA="7" HLASY="1" PROC_HLASU="0.02"/>
<HLASY_STRANA KSTRANA="9" HLASY="10" PROC_HLASU="0.28"/>
<HLASY_STRANA KSTRANA="10" HLASY="9" PROC_HLASU="0.25"/>
<HLASY_STRANA KSTRANA="11" HLASY="184" PROC_HLASU="5.19"/>
<HLASY_STRANA KSTRANA="13" HLASY="9" PROC_HLASU="0.25"/>
<HLASY_STRANA KSTRANA="14" HLASY="2" PROC_HLASU="0.05"/>
<HLASY_STRANA KSTRANA="15" HLASY="22" PROC_HLASU="0.62"/>
<HLASY_STRANA KSTRANA="17" HLASY="175" PROC_HLASU="4.93"/>
<HLASY_STRANA KSTRANA="18" HLASY="18" PROC_HLASU="0.50"/>
<HLASY_STRANA KSTRANA="20" HLASY="658" PROC_HLASU="18.56"/>
<HLASY_STRANA KSTRANA="21" HLASY="371" PROC_HLASU="10.46"/>
<HLASY_STRANA KSTRANA="22" HLASY="2" PROC_HLASU="0.05"/>
<HLASY_STRANA KSTRANA="23" HLASY="195" PROC_HLASU="5.50"/>
<HLASY_STRANA KSTRANA="24" HLASY="5" PROC_HLASU="0.14"/>
</OBEC>
<OBEC CIS_OBEC="539350" NAZ_OBEC="Jinočany">
<UCAST OKRSKY_CELKEM="1" OKRSKY_ZPRAC="1" OKRSKY_ZPRAC_PROC="100.00" ZAPSANI_VOLICI="1052" VYDANE_OBALKY="682" UCAST_PROC="64.83" ODEVZDANE_OBALKY="682" PLATNE_HLASY="679" PLATNE_HLASY_PROC="99.56" />
<HLASY_STRANA KSTRANA="1" HLASY="60" PROC_HLASU="8.83"/>
<HLASY_STRANA KSTRANA="2" HLASY="22" PROC_HLASU="3.24"/>
<HLASY_STRANA KSTRANA="3" HLASY="30" PROC_HLASU="4.41"/>
<HLASY_STRANA KSTRANA="4" HLASY="148" PROC_HLASU="21.79"/>
<HLASY_STRANA KSTRANA="6" HLASY="52" PROC_HLASU="7.65"/>
<HLASY_STRANA KSTRANA="9" HLASY="3" PROC_HLASU="0.44"/>
<HLASY_STRANA KSTRANA="11" HLASY="32" PROC_HLASU="4.71"/>
<HLASY_STRANA KSTRANA="13" HLASY="2" PROC_HLASU="0.29"/>
<HLASY_STRANA KSTRANA="15" HLASY="42" PROC_HLASU="6.18"/>
<HLASY_STRANA KSTRANA="17" HLASY="34" PROC_HLASU="5.00"/>
<HLASY_STRANA KSTRANA="18" HLASY="7" PROC_HLASU="1.03"/>
<HLASY_STRANA KSTRANA="20" HLASY="150" PROC_HLASU="22.09"/>
<HLASY_STRANA KSTRANA="21" HLASY="65" PROC_HLASU="9.57"/>
<HLASY_STRANA KSTRANA="23" HLASY="31" PROC_HLASU="4.56"/>
<HLASY_STRANA KSTRANA="24" HLASY="1" PROC_HLASU="0.14"/>
</OBEC>
<OBEC CIS_OBEC="539414" NAZ_OBEC="Libčice nad Vltavou">
<UCAST OKRSKY_CELKEM="3" OKRSKY_ZPRAC="3" OKRSKY_ZPRAC_PROC="100.00" ZAPSANI_VOLICI="2637" VYDANE_OBALKY="1532" UCAST_PROC="58.10" ODEVZDANE_OBALKY="1532" PLATNE_HLASY="1510" PLATNE_HLASY_PROC="98.56" />
<HLASY_STRANA KSTRANA="1" HLASY="192" PROC_HLASU="12.71"/>
<HLASY_STRANA KSTRANA="2" HLASY="39" PROC_HLASU="2.58"/>
<HLASY_STRANA KSTRANA="3" HLASY="50" PROC_HLASU="3.31"/>
<HLASY_STRANA KSTRANA="4" HLASY="280" PROC_HLASU="18.54"/>
<HLASY_STRANA KSTRANA="5" HLASY="20" PROC_HLASU="1.32"/>
<HLASY_STRANA KSTRANA="6" HLASY="133" PROC_HLASU="8.80"/>
<HLASY_STRANA KSTRANA="7" HLASY="1" PROC_HLASU="0.06"/>
<HLASY_STRANA KSTRANA="9" HLASY="3" PROC_HLASU="0.19"/>
<HLASY_STRANA KSTRANA="10" HLASY="4" PROC_HLASU="0.26"/>
<HLASY_STRANA KSTRANA="11" HLASY="70" PROC_HLASU="4.63"/>
<HLASY_STRANA KSTRANA="13" HLASY="11" PROC_HLASU="0.72"/>
<HLASY_STRANA KSTRANA="15" HLASY="16" PROC_HLASU="1.05"/>
<HLASY_STRANA KSTRANA="17" HLASY="92" PROC_HLASU="6.09"/>
<HLASY_STRANA KSTRANA="18" HLASY="12" PROC_HLASU="0.79"/>
<HLASY_STRANA KSTRANA="20" HLASY="297" PROC_HLASU="19.66"/>
<HLASY_STRANA KSTRANA="21" HLASY="202" PROC_HLASU="13.37"/>
<HLASY_STRANA KSTRANA="22" HLASY="3" PROC_HLASU="0.19"/>
<HLASY_STRANA KSTRANA="23" HLASY="82" PROC_HLASU="5.43"/>
<HLASY_STRANA KSTRANA="24" HLASY="3" PROC_HLASU="0.19"/>
</OBEC>
<OBEC CIS_OBEC="539422" NAZ_OBEC="Libeř">
<UCAST OKRSKY_CELKEM="2" OKRSKY_ZPRAC="2" OKRSKY_ZPRAC_PROC="100.00" ZAPSANI_VOLICI="956" VYDANE_OBALKY="621" UCAST_PROC="64.96" ODEVZDANE_OBALKY="621" PLATNE_HLASY="621" PLATNE_HLASY_PROC="100.00" />
<HLASY_STRANA KSTRANA="1" HLASY="50" PROC_HLASU="8.05"/>
<HLASY_STRANA KSTRANA="2" HLASY="21" PROC_HLASU="3.38"/>
<HLASY_STRANA KSTRANA="3" HLASY="11" PROC_HLASU="1.77"/>
<HLASY_STRANA KSTRANA="4" HLASY="135" PROC_HLASU="21.73"/>
<HLASY_STRANA KSTRANA="5" HLASY="3" PROC_HLASU="0.48"/>
<HLASY_STRANA KSTRANA="6" HLASY="76" PROC_HLASU="12.23"/>
<HLASY_STRANA KSTRANA="9" HLASY="1" PROC_HLASU="0.16"/>
<HLASY_STRANA KSTRANA="10" HLASY="2" PROC_HLASU="0.32"/>
<HLASY_STRANA KSTRANA="11" HLASY="14" PROC_HLASU="2.25"/>
<HLASY_STRANA KSTRANA="13" HLASY="2" PROC_HLASU="0.32"/>
<HLASY_STRANA KSTRANA="15" HLASY="3" PROC_HLASU="0.48"/>
<HLASY_STRANA KSTRANA="17" HLASY="41" PROC_HLASU="6.60"/>
<HLASY_STRANA KSTRANA="18" HLASY="2" PROC_HLASU="0.32"/>
<HLASY_STRANA KSTRANA="20" HLASY="189" PROC_HLASU="30.43"/>
<HLASY_STRANA KSTRANA="21" HLASY="40" PROC_HLASU="6.44"/>
<HLASY_STRANA KSTRANA="23" HLASY="27" PROC_HLASU="4.34"/>
<HLASY_STRANA KSTRANA="24" HLASY="4" PROC_HLASU="0.64"/>
</OBEC>
<OBEC CIS_OBEC="539503" NAZ_OBEC="Ohrobec">
<UCAST OKRSKY_CELKEM="1" OKRSKY_ZPRAC="1" OKRSKY_ZPRAC_PROC="100.00" ZAPSANI_VOLICI="893" VYDANE_OBALKY="653" UCAST_PROC="73.12" ODEVZDANE_OBALKY="653" PLATNE_HLASY="650" PLATNE_HLASY_PROC="99.54" />
<HLASY_STRANA KSTRANA="1" HLASY="69" PROC_HLASU="10.61"/>
<HLASY_STRANA KSTRANA="2" HLASY="28" PROC_HLASU="4.30"/>
<HLASY_STRANA KSTRANA="3" HLASY="11" PROC_HLASU="1.69"/>
<HLASY_STRANA KSTRANA="4" HLASY="164" PROC_HLASU="25.23"/>
<HLASY_STRANA KSTRANA="5" HLASY="4" PROC_HLASU="0.61"/>
<HLASY_STRANA KSTRANA="6" HLASY="78" PROC_HLASU="12.00"/>
<HLASY_STRANA KSTRANA="11" HLASY="29" PROC_HLASU="4.46"/>
<HLASY_STRANA KSTRANA="13" HLASY="5" PROC_HLASU="0.76"/>
<HLASY_STRANA KSTRANA="15" HLASY="11" PROC_HLASU="1.69"/>
<HLASY_STRANA KSTRANA="17" HLASY="25" PROC_HLASU="3.84"/>
<HLASY_STRANA KSTRANA="18" HLASY="2" PROC_HLASU="0.30"/>
<HLASY_STRANA KSTRANA="20" HLASY="155" PROC_HLASU="23.84"/>
<HLASY_STRANA KSTRANA="21" HLASY="49" PROC_HLASU="7.53"/>
<HLASY_STRANA KSTRANA="23" HLASY="20" PROC_HLASU="3.07"/>
</OBEC>
<OBEC CIS_OBEC="539520" NAZ_OBEC="Ořech">
<UCAST OKRSKY_CELKEM="1" OKRSKY_ZPRAC="1" OKRSKY_ZPRAC_PROC="100.00" ZAPSANI_VOLICI="682" VYDANE_OBALKY="444" UCAST_PROC="65.10" ODEVZDANE_OBALKY="444" PLATNE_HLASY="439" PLATNE_HLASY_PROC="98.87" />
<HLASY_STRANA KSTRANA="1" HLASY="51" PROC_HLASU="11.61"/>
<HLASY_STRANA KSTRANA="2" HLASY="15" PROC_HLASU="3.41"/>
<HLASY_STRANA KSTRANA="3" HLASY="14" PROC_HLASU="3.18"/>
<HLASY_STRANA KSTRANA="4" HLASY="121" PROC_HLASU="27.56"/>
<HLASY_STRANA KSTRANA="6" HLASY="54" PROC_HLASU="12.30"/>
<HLASY_STRANA KSTRANA="9" HLASY="4" PROC_HLASU="0.91"/>
<HLASY_STRANA KSTRANA="10" HLASY="1" PROC_HLASU="0.22"/>
<HLASY_STRANA KSTRANA="11" HLASY="11" PROC_HLASU="2.50"/>
<HLASY_STRANA KSTRANA="14" HLASY="1" PROC_HLASU="0.22"/>
<HLASY_STRANA KSTRANA="15" HLASY="6" PROC_HLASU="1.36"/>
<HLASY_STRANA KSTRANA="17" HLASY="25" PROC_HLASU="5.69"/>
<HLASY_STRANA KSTRANA="18" HLASY="4" PROC_HLASU="0.91"/>
<HLASY_STRANA KSTRANA="20" HLASY="82" PROC_HLASU="18.67"/>
<HLASY_STRANA KSTRANA="21" HLASY="31" PROC_HLASU="7.06"/>
<HLASY_STRANA KSTRANA="23" HLASY="18" PROC_HLASU="4.10"/>
<HLASY_STRANA KSTRANA="24" HLASY="1" PROC_HLASU="0.22"/>
</OBEC>
<OBEC CIS_OBEC="539830" NAZ_OBEC="Vonoklasy">
<UCAST OKRSKY_CELKEM="1" OKRSKY_ZPRAC="1" OKRSKY_ZPRAC_PROC="100.00" ZAPSANI_VOLICI="403" VYDANE_OBALKY="254" UCAST_PROC="63.03" ODEVZDANE_OBALKY="254" PLATNE_HLASY="254" PLATNE_HLASY_PROC="100.00" />
<HLASY_STRANA KSTRANA="1" HLASY="28" PROC_HLASU="11.02"/>
<HLASY_STRANA KSTRANA="2" HLASY="8" PROC_HLASU="3.14"/>
<HLASY_STRANA KSTRANA="3" HLASY="13" PROC_HLASU="5.11"/>
<HLASY_STRANA KSTRANA="4" HLASY="53" PROC_HLASU="20.86"/>
<HLASY_STRANA KSTRANA="5" HLASY="1" PROC_HLASU="0.39"/>
<HLASY_STRANA KSTRANA="6" HLASY="45" PROC_HLASU="17.71"/>
<HLASY_STRANA KSTRANA="9" HLASY="4" PROC_HLASU="1.57"/>
<HLASY_STRANA KSTRANA="11" HLASY="3" PROC_HLASU="1.18"/>
<HLASY_STRANA KSTRANA="17" HLASY="4" PROC_HLASU="1.57"/>
<HLASY_STRANA KSTRANA="18" HLASY="1" PROC_HLASU="0.39"/>
<HLASY_STRANA KSTRANA="20" HLASY="48" PROC_HLASU="18.89"/>
<HLASY_STRANA KSTRANA="21" HLASY="26" PROC_HLASU="10.23"/>
<HLASY_STRANA KSTRANA="23" HLASY="20" PROC_HLASU="7.87"/>
</OBEC>
<OBEC CIS_OBEC="571211" NAZ_OBEC="Klínec">
<UCAST OKRSKY_CELKEM="1" OKRSKY_ZPRAC="1" OKRSKY_ZPRAC_PROC="100.00" ZAPSANI_VOLICI="483" VYDANE_OBALKY="315" UCAST_PROC="65.22" ODEVZDANE_OBALKY="315" PLATNE_HLASY="310" PLATNE_HLASY_PROC="98.41" />
<HLASY_STRANA KSTRANA="1" HLASY="39" PROC_HLASU="12.58"/>
<HLASY_STRANA KSTRANA="2" HLASY="11" PROC_HLASU="3.54"/>
<HLASY_STRANA KSTRANA="3" HLASY="4" PROC_HLASU="1.29"/>
<HLASY_STRANA KSTRANA="4" HLASY="63" PROC_HLASU="20.32"/>
<HLASY_STRANA KSTRANA="6" HLASY="27" PROC_HLASU="8.70"/>
<HLASY_STRANA KSTRANA="9" HLASY="1" PROC_HLASU="0.32"/>
<HLASY_STRANA KSTRANA="10" HLASY="1" PROC_HLASU="0.32"/>
<HLASY_STRANA KSTRANA="11" HLASY="17" PROC_HLASU="5.48"/>
<HLASY_STRANA KSTRANA="13" HLASY="1" PROC_HLASU="0.32"/>
<HLASY_STRANA KSTRANA="15" HLASY="3" PROC_HLASU="0.96"/>
<HLASY_STRANA KSTRANA="17" HLASY="20" PROC_HLASU="6.45"/>
<HLASY_STRANA KSTRANA="20" HLASY="86" PROC_HLASU="27.74"/>
<HLASY_STRANA KSTRANA="21" HLASY="25" PROC_HLASU="8.06"/>
<HLASY_STRANA KSTRANA="23" HLASY="10" PROC_HLASU="3.22"/>
<HLASY_STRANA KSTRANA="24" HLASY="2" PROC_HLASU="0.64"/>
</OBEC>
<OBEC CIS_OBEC="531723" NAZ_OBEC="Rudná">
<UCAST OKRSKY_CELKEM="2" OKRSKY_ZPRAC="2" OKRSKY_ZPRAC_PROC="100.00" ZAPSANI_VOLICI="3448" VYDANE_OBALKY="2294" UCAST_PROC="66.53" ODEVZDANE_OBALKY="2292" PLATNE_HLASY="2277" PLATNE_HLASY_PROC="99.35" />
<HLASY_STRANA KSTRANA="1" HLASY="248" PROC_HLASU="10.89"/>
<HLASY_STRANA KSTRANA="2" HLASY="84" PROC_HLASU="3.68"/>
<HLASY_STRANA KSTRANA="3" HLASY="75" PROC_HLASU="3.29"/>
<HLASY_STRANA KSTRANA="4" HLASY="578" PROC_HLASU="25.38"/>
<HLASY_STRANA KSTRANA="5" HLASY="11" PROC_HLASU="0.48"/>
<HLASY_STRANA KSTRANA="6" HLASY="261" PROC_HLASU="11.46"/>
<HLASY_STRANA KSTRANA="7" HLASY="2" PROC_HLASU="0.08"/>
<HLASY_STRANA KSTRANA="9" HLASY="6" PROC_HLASU="0.26"/>
<HLASY_STRANA KSTRANA="10" HLASY="10" PROC_HLASU="0.43"/>
<HLASY_STRANA KSTRANA="11" HLASY="97" PROC_HLASU="4.25"/>
<HLASY_STRANA KSTRANA="13" HLASY="9" PROC_HLASU="0.39"/>
<HLASY_STRANA KSTRANA="14" HLASY="2" PROC_HLASU="0.08"/>
<HLASY_STRANA KSTRANA="15" HLASY="23" PROC_HLASU="1.01"/>
<HLASY_STRANA KSTRANA="17" HLASY="101" PROC_HLASU="4.43"/>
<HLASY_STRANA KSTRANA="18" HLASY="12" PROC_HLASU="0.52"/>
<HLASY_STRANA KSTRANA="20" HLASY="461" PROC_HLASU="20.24"/>
<HLASY_STRANA KSTRANA="21" HLASY="160" PROC_HLASU="7.02"/>
<HLASY_STRANA KSTRANA="23" HLASY="130" PROC_HLASU="5.70"/>
<HLASY_STRANA KSTRANA="24" HLASY="7" PROC_HLASU="0.30"/>
</OBEC>
<OBEC CIS_OBEC="531821" NAZ_OBEC="Tachlovice">
<UCAST OKRSKY_CELKEM="1" OKRSKY_ZPRAC="1" OKRSKY_ZPRAC_PROC="100.00" ZAPSANI_VOLICI="695" VYDANE_OBALKY="443" UCAST_PROC="63.74" ODEVZDANE_OBALKY="443" PLATNE_HLASY="441" PLATNE_HLASY_PROC="99.55" />
<HLASY_STRANA KSTRANA="1" HLASY="59" PROC_HLASU="13.37"/>
<HLASY_STRANA KSTRANA="2" HLASY="19" PROC_HLASU="4.30"/>
<HLASY_STRANA KSTRANA="3" HLASY="13" PROC_HLASU="2.94"/>
<HLASY_STRANA KSTRANA="4" HLASY="95" PROC_HLASU="21.54"/>
<HLASY_STRANA KSTRANA="5" HLASY="2" PROC_HLASU="0.45"/>
<HLASY_STRANA KSTRANA="6" HLASY="40" PROC_HLASU="9.07"/>
<HLASY_STRANA KSTRANA="9" HLASY="3" PROC_HLASU="0.68"/>
<HLASY_STRANA KSTRANA="10" HLASY="1" PROC_HLASU="0.22"/>
<HLASY_STRANA KSTRANA="11" HLASY="23" PROC_HLASU="5.21"/>
<HLASY_STRANA KSTRANA="15" HLASY="5" PROC_HLASU="1.13"/>
<HLASY_STRANA KSTRANA="17" HLASY="18" PROC_HLASU="4.08"/>
<HLASY_STRANA KSTRANA="18" HLASY="1" PROC_HLASU="0.22"/>
<HLASY_STRANA KSTRANA="20" HLASY="100" PROC_HLASU="22.67"/>
<HLASY_STRANA KSTRANA="21" HLASY="46" PROC_HLASU="10.43"/>
<HLASY_STRANA KSTRANA="23" HLASY="16" PROC_HLASU="3.62"/>
</OBEC>
<OBEC CIS_OBEC="539121" NAZ_OBEC="Černolice">
<UCAST OKRSKY_CELKEM="1" OKRSKY_ZPRAC="1" OKRSKY_ZPRAC_PROC="100.00" ZAPSANI_VOLICI="285" VYDANE_OBALKY="198" UCAST_PROC="69.47" ODEVZDANE_OBALKY="198" PLATNE_HLASY="196" PLATNE_HLASY_PROC="98.99" />
<HLASY_STRANA KSTRANA="1" HLASY="25" PROC_HLASU="12.75"/>
<HLASY_STRANA KSTRANA="2" HLASY="3" PROC_HLASU="1.53"/>
<HLASY_STRANA KSTRANA="3" HLASY="6" PROC_HLASU="3.06"/>
<HLASY_STRANA KSTRANA="4" HLASY="52" PROC_HLASU="26.53"/>
<HLASY_STRANA KSTRANA="5" HLASY="1" PROC_HLASU="0.51"/>
<HLASY_STRANA KSTRANA="6" HLASY="30" PROC_HLASU="15.30"/>
<HLASY_STRANA KSTRANA="9" HLASY="4" PROC_HLASU="2.04"/>
<HLASY_STRANA KSTRANA="10" HLASY="1" PROC_HLASU="0.51"/>
<HLASY_STRANA KSTRANA="11" HLASY="4" PROC_HLASU="2.04"/>
<HLASY_STRANA KSTRANA="15" HLASY="1" PROC_HLASU="0.51"/>
<HLASY_STRANA KSTRANA="17" HLASY="9" PROC_HLASU="4.59"/>
<HLASY_STRANA KSTRANA="20" HLASY="40" PROC_HLASU="20.40"/>
<HLASY_STRANA KSTRANA="21" HLASY="13" PROC_HLASU="6.63"/>
<HLASY_STRANA KSTRANA="23" HLASY="7" PROC_HLASU="3.57"/>
</OBEC>
<OBEC CIS_OBEC="539511" NAZ_OBEC="Okrouhlo">
<UCAST OKRSKY_CELKEM="1" OKRSKY_ZPRAC="1" OKRSKY_ZPRAC_PROC="100.00" ZAPSANI_VOLICI="501" VYDANE_OBALKY="338" UCAST_PROC="67.47" ODEVZDANE_OBALKY="338" PLATNE_HLASY="334" PLATNE_HLASY_PROC="98.82" />
<HLASY_STRANA KSTRANA="1" HLASY="36" PROC_HLASU="10.77"/>
<HLASY_STRANA KSTRANA="2" HLASY="11" PROC_HLASU="3.29"/>
<HLASY_STRANA KSTRANA="3" HLASY="17" PROC_HLASU="5.08"/>
<HLASY_STRANA KSTRANA="4" HLASY="55" PROC_HLASU="16.46"/>
<HLASY_STRANA KSTRANA="5" HLASY="4" PROC_HLASU="1.19"/>
<HLASY_STRANA KSTRANA="6" HLASY="27" PROC_HLASU="8.08"/>
<HLASY_STRANA KSTRANA="7" HLASY="1" PROC_HLASU="0.29"/>
<HLASY_STRANA KSTRANA="9" HLASY="2" PROC_HLASU="0.59"/>
<HLASY_STRANA KSTRANA="10" HLASY="3" PROC_HLASU="0.89"/>
<HLASY_STRANA KSTRANA="11" HLASY="7" PROC_HLASU="2.09"/>
<HLASY_STRANA KSTRANA="15" HLASY="8" PROC_HLASU="2.39"/>
<HLASY_STRANA KSTRANA="17" HLASY="25" PROC_HLASU="7.48"/>
<HLASY_STRANA KSTRANA="18" HLASY="2" PROC_HLASU="0.59"/>
<HLASY_STRANA KSTRANA="20" HLASY="94" PROC_HLASU="28.14"/>
<HLASY_STRANA KSTRANA="21" HLASY="26" PROC_HLASU="7.78"/>
<HLASY_STRANA KSTRANA="23" HLASY="13" PROC_HLASU="3.89"/>
<HLASY_STRANA KSTRANA="24" HLASY="3" PROC_HLASU="0.89"/>
</OBEC>
<OBEC CIS_OBEC="539597" NAZ_OBEC="Psáry">
<UCAST OKRSKY_CELKEM="1" OKRSKY_ZPRAC="1" OKRSKY_ZPRAC_PROC="100.00" ZAPSANI_VOLICI="2591" VYDANE_OBALKY="1695" UCAST_PROC="65.42" ODEVZDANE_OBALKY="1695" PLATNE_HLASY="1688" PLATNE_HLASY_PROC="99.59" />
<HLASY_STRANA KSTRANA="1" HLASY="163" PROC_HLASU="9.65"/>
<HLASY_STRANA KSTRANA="2" HLASY="75" PROC_HLASU="4.44"/>
<HLASY_STRANA KSTRANA="3" HLASY="38" PROC_HLASU="2.25"/>
<HLASY_STRANA KSTRANA="4" HLASY="419" PROC_HLASU="24.82"/>
<HLASY_STRANA KSTRANA="5" HLASY="9" PROC_HLASU="0.53"/>
<HLASY_STRANA KSTRANA="6" HLASY="184" PROC_HLASU="10.90"/>
<HLASY_STRANA KSTRANA="9" HLASY="12" PROC_HLASU="0.71"/>
<HLASY_STRANA KSTRANA="10" HLASY="7" PROC_HLASU="0.41"/>
<HLASY_STRANA KSTRANA="11" HLASY="50" PROC_HLASU="2.96"/>
<HLASY_STRANA KSTRANA="13" HLASY="1" PROC_HLASU="0.05"/>
<HLASY_STRANA KSTRANA="14" HLASY="2" PROC_HLASU="0.11"/>
<HLASY_STRANA KSTRANA="15" HLASY="19" PROC_HLASU="1.12"/>
<HLASY_STRANA KSTRANA="17" HLASY="81" PROC_HLASU="4.79"/>
<HLASY_STRANA KSTRANA="18" HLASY="9" PROC_HLASU="0.53"/>
<HLASY_STRANA KSTRANA="20" HLASY="406" PROC_HLASU="24.05"/>
<HLASY_STRANA KSTRANA="21" HLASY="127" PROC_HLASU="7.52"/>
<HLASY_STRANA KSTRANA="23" HLASY="84" PROC_HLASU="4.97"/>
<HLASY_STRANA KSTRANA="24" HLASY="2" PROC_HLASU="0.11"/>
</OBEC>
<OBEC CIS_OBEC="539660" NAZ_OBEC="Slapy">
<UCAST OKRSKY_CELKEM="1" OKRSKY_ZPRAC="1" OKRSKY_ZPRAC_PROC="100.00" ZAPSANI_VOLICI="689" VYDANE_OBALKY="455" UCAST_PROC="66.04" ODEVZDANE_OBALKY="455" PLATNE_HLASY="452" PLATNE_HLASY_PROC="99.34" />
<HLASY_STRANA KSTRANA="1" HLASY="83" PROC_HLASU="18.36"/>
<HLASY_STRANA KSTRANA="2" HLASY="19" PROC_HLASU="4.20"/>
<HLASY_STRANA KSTRANA="3" HLASY="9" PROC_HLASU="1.99"/>
<HLASY_STRANA KSTRANA="4" HLASY="97" PROC_HLASU="21.46"/>
<HLASY_STRANA KSTRANA="5" HLASY="7" PROC_HLASU="1.54"/>
<HLASY_STRANA KSTRANA="6" HLASY="43" PROC_HLASU="9.51"/>
<HLASY_STRANA KSTRANA="10" HLASY="2" PROC_HLASU="0.44"/>
<HLASY_STRANA KSTRANA="11" HLASY="17" PROC_HLASU="3.76"/>
<HLASY_STRANA KSTRANA="13" HLASY="1" PROC_HLASU="0.22"/>
<HLASY_STRANA KSTRANA="15" HLASY="11" PROC_HLASU="2.43"/>
<HLASY_STRANA KSTRANA="17" HLASY="22" PROC_HLASU="4.86"/>
<HLASY_STRANA KSTRANA="18" HLASY="5" PROC_HLASU="1.10"/>
<HLASY_STRANA KSTRANA="20" HLASY="80" PROC_HLASU="17.69"/>
<HLASY_STRANA KSTRANA="21" HLASY="38" PROC_HLASU="8.40"/>
<HLASY_STRANA KSTRANA="23" HLASY="16" PROC_HLASU="3.53"/>
<HLASY_STRANA KSTRANA="24" HLASY="2" PROC_HLASU="0.44"/>
</OBEC>
<OBEC CIS_OBEC="539856" NAZ_OBEC="Všenory">
<UCAST OKRSKY_CELKEM="1" OKRSKY_ZPRAC="1" OKRSKY_ZPRAC_PROC="100.00" ZAPSANI_VOLICI="1231" VYDANE_OBALKY="849" UCAST_PROC="68.97" ODEVZDANE_OBALKY="849" PLATNE_HLASY="840" PLATNE_HLASY_PROC="98.94" />
<HLASY_STRANA KSTRANA="1" HLASY="96" PROC_HLASU="11.42"/>
<HLASY_STRANA KSTRANA="2" HLASY="25" PROC_HLASU="2.97"/>
<HLASY_STRANA KSTRANA="3" HLASY="26" PROC_HLASU="3.09"/>
<HLASY_STRANA KSTRANA="4" HLASY="184" PROC_HLASU="21.90"/>
<HLASY_STRANA KSTRANA="5" HLASY="10" PROC_HLASU="1.19"/>
<HLASY_STRANA KSTRANA="6" HLASY="123" PROC_HLASU="14.64"/>
<HLASY_STRANA KSTRANA="9" HLASY="2" PROC_HLASU="0.23"/>
<HLASY_STRANA KSTRANA="10" HLASY="2" PROC_HLASU="0.23"/>
<HLASY_STRANA KSTRANA="11" HLASY="45" PROC_HLASU="5.35"/>
<HLASY_STRANA KSTRANA="13" HLASY="3" PROC_HLASU="0.35"/>
<HLASY_STRANA KSTRANA="14" HLASY="1" PROC_HLASU="0.11"/>
<HLASY_STRANA KSTRANA="15" HLASY="13" PROC_HLASU="1.54"/>
<HLASY_STRANA KSTRANA="17" HLASY="24" PROC_HLASU="2.85"/>
<HLASY_STRANA KSTRANA="18" HLASY="4" PROC_HLASU="0.47"/>
<HLASY_STRANA KSTRANA="20" HLASY="167" PROC_HLASU="19.88"/>
<HLASY_STRANA KSTRANA="21" HLASY="56" PROC_HLASU="6.66"/>
<HLASY_STRANA KSTRANA="23" HLASY="56" PROC_HLASU="6.66"/>
<HLASY_STRANA KSTRANA="24" HLASY="3" PROC_HLASU="0.35"/>
</OBEC>
<OBEC CIS_OBEC="539198" NAZ_OBEC="Dobřichovice">
<UCAST OKRSKY_CELKEM="3" OKRSKY_ZPRAC="3" OKRSKY_ZPRAC_PROC="100.00" ZAPSANI_VOLICI="2627" VYDANE_OBALKY="1915" UCAST_PROC="72.90" ODEVZDANE_OBALKY="1914" PLATNE_HLASY="1902" PLATNE_HLASY_PROC="99.37" />
<HLASY_STRANA KSTRANA="1" HLASY="199" PROC_HLASU="10.46"/>
<HLASY_STRANA KSTRANA="2" HLASY="71" PROC_HLASU="3.73"/>
<HLASY_STRANA KSTRANA="3" HLASY="52" PROC_HLASU="2.73"/>
<HLASY_STRANA KSTRANA="4" HLASY="491" PROC_HLASU="25.81"/>
<HLASY_STRANA KSTRANA="5" HLASY="6" PROC_HLASU="0.31"/>
<HLASY_STRANA KSTRANA="6" HLASY="393" PROC_HLASU="20.66"/>
<HLASY_STRANA KSTRANA="7" HLASY="2" PROC_HLASU="0.10"/>
<HLASY_STRANA KSTRANA="9" HLASY="14" PROC_HLASU="0.73"/>
<HLASY_STRANA KSTRANA="10" HLASY="7" PROC_HLASU="0.36"/>
<HLASY_STRANA KSTRANA="11" HLASY="85" PROC_HLASU="4.46"/>
<HLASY_STRANA KSTRANA="13" HLASY="4" PROC_HLASU="0.21"/>
<HLASY_STRANA KSTRANA="14" HLASY="2" PROC_HLASU="0.10"/>
<HLASY_STRANA KSTRANA="15" HLASY="16" PROC_HLASU="0.84"/>
<HLASY_STRANA KSTRANA="17" HLASY="58" PROC_HLASU="3.04"/>
<HLASY_STRANA KSTRANA="18" HLASY="6" PROC_HLASU="0.31"/>
<HLASY_STRANA KSTRANA="20" HLASY="294" PROC_HLASU="15.45"/>
<HLASY_STRANA KSTRANA="21" HLASY="89" PROC_HLASU="4.67"/>
<HLASY_STRANA KSTRANA="23" HLASY="111" PROC_HLASU="5.83"/>
<HLASY_STRANA KSTRANA="24" HLASY="2" PROC_HLASU="0.10"/>
</OBEC>
<OBEC CIS_OBEC="539228" NAZ_OBEC="Holubice">
<UCAST OKRSKY_CELKEM="1" OKRSKY_ZPRAC="1" OKRSKY_ZPRAC_PROC="100.00" ZAPSANI_VOLICI="1125" VYDANE_OBALKY="726" UCAST_PROC="64.53" ODEVZDANE_OBALKY="726" PLATNE_HLASY="721" PLATNE_HLASY_PROC="99.31" />
<HLASY_STRANA KSTRANA="1" HLASY="101" PROC_HLASU="14.00"/>
<HLASY_STRANA KSTRANA="2" HLASY="38" PROC_HLASU="5.27"/>
<HLASY_STRANA KSTRANA="3" HLASY="13" PROC_HLASU="1.80"/>
<HLASY_STRANA KSTRANA="4" HLASY="157" PROC_HLASU="21.77"/>
<HLASY_STRANA KSTRANA="5" HLASY="4" PROC_HLASU="0.55"/>
<HLASY_STRANA KSTRANA="6" HLASY="69" PROC_HLASU="9.57"/>
<HLASY_STRANA KSTRANA="7" HLASY="1" PROC_HLASU="0.13"/>
<HLASY_STRANA KSTRANA="9" HLASY="6" PROC_HLASU="0.83"/>
<HLASY_STRANA KSTRANA="10" HLASY="3" PROC_HLASU="0.41"/>
<HLASY_STRANA KSTRANA="11" HLASY="18" PROC_HLASU="2.49"/>
<HLASY_STRANA KSTRANA="13" HLASY="1" PROC_HLASU="0.13"/>
<HLASY_STRANA KSTRANA="15" HLASY="9" PROC_HLASU="1.24"/>
<HLASY_STRANA KSTRANA="17" HLASY="41" PROC_HLASU="5.68"/>
<HLASY_STRANA KSTRANA="18" HLASY="1" PROC_HLASU="0.13"/>
<HLASY_STRANA KSTRANA="20" HLASY="150" PROC_HLASU="20.80"/>
<HLASY_STRANA KSTRANA="21" HLASY="73" PROC_HLASU="10.12"/>
<HLASY_STRANA KSTRANA="23" HLASY="34" PROC_HLASU="4.71"/>
<HLASY_STRANA KSTRANA="24" HLASY="2" PROC_HLASU="0.27"/>
</OBEC>
<OBEC CIS_OBEC="539261" NAZ_OBEC="Hvozdnice">
<UCAST OKRSKY_CELKEM="1" OKRSKY_ZPRAC="1" OKRSKY_ZPRAC_PROC="100.00" ZAPSANI_VOLICI="367" VYDANE_OBALKY="278" UCAST_PROC="75.75" ODEVZDANE_OBALKY="278" PLATNE_HLASY="277" PLATNE_HLASY_PROC="99.64" />
<HLASY_STRANA KSTRANA="1" HLASY="49" PROC_HLASU="17.68"/>
<HLASY_STRANA KSTRANA="2" HLASY="9" PROC_HLASU="3.24"/>
<HLASY_STRANA KSTRANA="3" HLASY="18" PROC_HLASU="6.49"/>
<HLASY_STRANA KSTRANA="4" HLASY="61" PROC_HLASU="22.02"/>
<HLASY_STRANA KSTRANA="5" HLASY="1" PROC_HLASU="0.36"/>
<HLASY_STRANA KSTRANA="6" HLASY="27" PROC_HLASU="9.74"/>
<HLASY_STRANA KSTRANA="9" HLASY="3" PROC_HLASU="1.08"/>
<HLASY_STRANA KSTRANA="11" HLASY="10" PROC_HLASU="3.61"/>
<HLASY_STRANA KSTRANA="14" HLASY="1" PROC_HLASU="0.36"/>
<HLASY_STRANA KSTRANA="15" HLASY="4" PROC_HLASU="1.44"/>
<HLASY_STRANA KSTRANA="17" HLASY="14" PROC_HLASU="5.05"/>
<HLASY_STRANA KSTRANA="18" HLASY="1" PROC_HLASU="0.36"/>
<HLASY_STRANA KSTRANA="20" HLASY="50" PROC_HLASU="18.05"/>
<HLASY_STRANA KSTRANA="21" HLASY="18" PROC_HLASU="6.49"/>
<HLASY_STRANA KSTRANA="23" HLASY="10" PROC_HLASU="3.61"/>
<HLASY_STRANA KSTRANA="24" HLASY="1" PROC_HLASU="0.36"/>
</OBEC>
<OBEC CIS_OBEC="539295" NAZ_OBEC="Chrášťany">
<UCAST OKRSKY_CELKEM="1" OKRSKY_ZPRAC="1" OKRSKY_ZPRAC_PROC="100.00" ZAPSANI_VOLICI="589" VYDANE_OBALKY="373" UCAST_PROC="63.33" ODEVZDANE_OBALKY="372" PLATNE_HLASY="370" PLATNE_HLASY_PROC="99.46" />
<HLASY_STRANA KSTRANA="1" HLASY="62" PROC_HLASU="16.75"/>
<HLASY_STRANA KSTRANA="2" HLASY="12" PROC_HLASU="3.24"/>
<HLASY_STRANA KSTRANA="3" HLASY="7" PROC_HLASU="1.89"/>
<HLASY_STRANA KSTRANA="4" HLASY="97" PROC_HLASU="26.21"/>
<HLASY_STRANA KSTRANA="6" HLASY="25" PROC_HLASU="6.75"/>
<HLASY_STRANA KSTRANA="9" HLASY="3" PROC_HLASU="0.81"/>
<HLASY_STRANA KSTRANA="11" HLASY="4" PROC_HLASU="1.08"/>
<HLASY_STRANA KSTRANA="14" HLASY="1" PROC_HLASU="0.27"/>
<HLASY_STRANA KSTRANA="15" HLASY="5" PROC_HLASU="1.35"/>
<HLASY_STRANA KSTRANA="17" HLASY="14" PROC_HLASU="3.78"/>
<HLASY_STRANA KSTRANA="18" HLASY="3" PROC_HLASU="0.81"/>
<HLASY_STRANA KSTRANA="20" HLASY="75" PROC_HLASU="20.27"/>
<HLASY_STRANA KSTRANA="21" HLASY="41" PROC_HLASU="11.08"/>
<HLASY_STRANA KSTRANA="23" HLASY="20" PROC_HLASU="5.40"/>
<HLASY_STRANA KSTRANA="24" HLASY="1" PROC_HLASU="0.27"/>
</OBEC>
<OBEC CIS_OBEC="539309" NAZ_OBEC="Chýně">
<UCAST OKRSKY_CELKEM="1" OKRSKY_ZPRAC="1" OKRSKY_ZPRAC_PROC="100.00" ZAPSANI_VOLICI="1433" VYDANE_OBALKY="987" UCAST_PROC="68.88" ODEVZDANE_OBALKY="987" PLATNE_HLASY="979" PLATNE_HLASY_PROC="99.19" />
<HLASY_STRANA KSTRANA="1" HLASY="102" PROC_HLASU="10.41"/>
<HLASY_STRANA KSTRANA="2" HLASY="31" PROC_HLASU="3.16"/>
<HLASY_STRANA KSTRANA="3" HLASY="26" PROC_HLASU="2.65"/>
<HLASY_STRANA KSTRANA="4" HLASY="292" PROC_HLASU="29.82"/>
<HLASY_STRANA KSTRANA="5" HLASY="11" PROC_HLASU="1.12"/>
<HLASY_STRANA KSTRANA="6" HLASY="80" PROC_HLASU="8.17"/>
<HLASY_STRANA KSTRANA="7" HLASY="1" PROC_HLASU="0.10"/>
<HLASY_STRANA KSTRANA="10" HLASY="3" PROC_HLASU="0.30"/>
<HLASY_STRANA KSTRANA="11" HLASY="35" PROC_HLASU="3.57"/>
<HLASY_STRANA KSTRANA="14" HLASY="1" PROC_HLASU="0.10"/>
<HLASY_STRANA KSTRANA="15" HLASY="16" PROC_HLASU="1.63"/>
<HLASY_STRANA KSTRANA="17" HLASY="47" PROC_HLASU="4.80"/>
<HLASY_STRANA KSTRANA="18" HLASY="3" PROC_HLASU="0.30"/>
<HLASY_STRANA KSTRANA="20" HLASY="215" PROC_HLASU="21.96"/>
<HLASY_STRANA KSTRANA="21" HLASY="79" PROC_HLASU="8.06"/>
<HLASY_STRANA KSTRANA="23" HLASY="36" PROC_HLASU="3.67"/>
<HLASY_STRANA KSTRANA="24" HLASY="1" PROC_HLASU="0.10"/>
</OBEC>
<OBEC CIS_OBEC="539546" NAZ_OBEC="Petrov">
<UCAST OKRSKY_CELKEM="1" OKRSKY_ZPRAC="1" OKRSKY_ZPRAC_PROC="100.00" ZAPSANI_VOLICI="482" VYDANE_OBALKY="334" UCAST_PROC="69.29" ODEVZDANE_OBALKY="334" PLATNE_HLASY="332" PLATNE_HLASY_PROC="99.40" />
<HLASY_STRANA KSTRANA="1" HLASY="56" PROC_HLASU="16.86"/>
<HLASY_STRANA KSTRANA="2" HLASY="6" PROC_HLASU="1.80"/>
<HLASY_STRANA KSTRANA="3" HLASY="5" PROC_HLASU="1.50"/>
<HLASY_STRANA KSTRANA="4" HLASY="82" PROC_HLASU="24.69"/>
<HLASY_STRANA KSTRANA="6" HLASY="31" PROC_HLASU="9.33"/>
<HLASY_STRANA KSTRANA="9" HLASY="3" PROC_HLASU="0.90"/>
<HLASY_STRANA KSTRANA="10" HLASY="3" PROC_HLASU="0.90"/>
<HLASY_STRANA KSTRANA="11" HLASY="12" PROC_HLASU="3.61"/>
<HLASY_STRANA KSTRANA="15" HLASY="8" PROC_HLASU="2.40"/>
<HLASY_STRANA KSTRANA="17" HLASY="14" PROC_HLASU="4.21"/>
<HLASY_STRANA KSTRANA="18" HLASY="2" PROC_HLASU="0.60"/>
<HLASY_STRANA KSTRANA="20" HLASY="60" PROC_HLASU="18.07"/>
<HLASY_STRANA KSTRANA="21" HLASY="29" PROC_HLASU="8.73"/>
<HLASY_STRANA KSTRANA="23" HLASY="21" PROC_HLASU="6.32"/>
</OBEC>
<OBEC CIS_OBEC="539627" NAZ_OBEC="Roztoky">
<UCAST OKRSKY_CELKEM="7" OKRSKY_ZPRAC="7" OKRSKY_ZPRAC_PROC="100.00" ZAPSANI_VOLICI="5787" VYDANE_OBALKY="4070" UCAST_PROC="70.33" ODEVZDANE_OBALKY="4063" PLATNE_HLASY="4039" PLATNE_HLASY_PROC="99.41" />
<HLASY_STRANA KSTRANA="1" HLASY="514" PROC_HLASU="12.72"/>
<HLASY_STRANA KSTRANA="2" HLASY="132" PROC_HLASU="3.26"/>
<HLASY_STRANA KSTRANA="3" HLASY="141" PROC_HLASU="3.49"/>
<HLASY_STRANA KSTRANA="4" HLASY="1174" PROC_HLASU="29.06"/>
<HLASY_STRANA KSTRANA="5" HLASY="10" PROC_HLASU="0.24"/>
<HLASY_STRANA KSTRANA="6" HLASY="406" PROC_HLASU="10.05"/>
<HLASY_STRANA KSTRANA="9" HLASY="21" PROC_HLASU="0.51"/>
<HLASY_STRANA KSTRANA="10" HLASY="9" PROC_HLASU="0.22"/>
<HLASY_STRANA KSTRANA="11" HLASY="240" PROC_HLASU="5.94"/>
<HLASY_STRANA KSTRANA="13" HLASY="5" PROC_HLASU="0.12"/>
<HLASY_STRANA KSTRANA="14" HLASY="3" PROC_HLASU="0.07"/>
<HLASY_STRANA KSTRANA="15" HLASY="22" PROC_HLASU="0.54"/>
<HLASY_STRANA KSTRANA="17" HLASY="149" PROC_HLASU="3.68"/>
<HLASY_STRANA KSTRANA="18" HLASY="13" PROC_HLASU="0.32"/>
<HLASY_STRANA KSTRANA="20" HLASY="598" PROC_HLASU="14.80"/>
<HLASY_STRANA KSTRANA="21" HLASY="278" PROC_HLASU="6.88"/>
<HLASY_STRANA KSTRANA="23" HLASY="307" PROC_HLASU="7.60"/>
<HLASY_STRANA KSTRANA="24" HLASY="17" PROC_HLASU="0.42"/>
</OBEC>
<OBEC CIS_OBEC="539643" NAZ_OBEC="Řevnice">
<UCAST OKRSKY_CELKEM="2" OKRSKY_ZPRAC="2" OKRSKY_ZPRAC_PROC="100.00" ZAPSANI_VOLICI="2575" VYDANE_OBALKY="1809" UCAST_PROC="70.25" ODEVZDANE_OBALKY="1808" PLATNE_HLASY="1789" PLATNE_HLASY_PROC="98.95" />
<HLASY_STRANA KSTRANA="1" HLASY="258" PROC_HLASU="14.42"/>
<HLASY_STRANA KSTRANA="2" HLASY="49" PROC_HLASU="2.73"/>
<HLASY_STRANA KSTRANA="3" HLASY="45" PROC_HLASU="2.51"/>
<HLASY_STRANA KSTRANA="4" HLASY="398" PROC_HLASU="22.24"/>
<HLASY_STRANA KSTRANA="5" HLASY="9" PROC_HLASU="0.50"/>
<HLASY_STRANA KSTRANA="6" HLASY="279" PROC_HLASU="15.59"/>
<HLASY_STRANA KSTRANA="7" HLASY="3" PROC_HLASU="0.16"/>
<HLASY_STRANA KSTRANA="9" HLASY="6" PROC_HLASU="0.33"/>
<HLASY_STRANA KSTRANA="10" HLASY="9" PROC_HLASU="0.50"/>
<HLASY_STRANA KSTRANA="11" HLASY="94" PROC_HLASU="5.25"/>
<HLASY_STRANA KSTRANA="13" HLASY="6" PROC_HLASU="0.33"/>
<HLASY_STRANA KSTRANA="15" HLASY="8" PROC_HLASU="0.44"/>
<HLASY_STRANA KSTRANA="17" HLASY="71" PROC_HLASU="3.96"/>
<HLASY_STRANA KSTRANA="18" HLASY="13" PROC_HLASU="0.72"/>
<HLASY_STRANA KSTRANA="20" HLASY="289" PROC_HLASU="16.15"/>
<HLASY_STRANA KSTRANA="21" HLASY="129" PROC_HLASU="7.21"/>
<HLASY_STRANA KSTRANA="22" HLASY="1" PROC_HLASU="0.05"/>
<HLASY_STRANA KSTRANA="23" HLASY="119" PROC_HLASU="6.65"/>
<HLASY_STRANA KSTRANA="24" HLASY="3" PROC_HLASU="0.16"/>
</OBEC>
<OBEC CIS_OBEC="539805" NAZ_OBEC="Únětice">
<UCAST OKRSKY_CELKEM="1" OKRSKY_ZPRAC="1" OKRSKY_ZPRAC_PROC="100.00" ZAPSANI_VOLICI="469" VYDANE_OBALKY="336" UCAST_PROC="71.64" ODEVZDANE_OBALKY="336" PLATNE_HLASY="336" PLATNE_HLASY_PROC="100.00" />
<HLASY_STRANA KSTRANA="1" HLASY="27" PROC_HLASU="8.03"/>
<HLASY_STRANA KSTRANA="2" HLASY="8" PROC_HLASU="2.38"/>
<HLASY_STRANA KSTRANA="3" HLASY="11" PROC_HLASU="3.27"/>
<HLASY_STRANA KSTRANA="4" HLASY="130" PROC_HLASU="38.69"/>
<HLASY_STRANA KSTRANA="5" HLASY="1" PROC_HLASU="0.29"/>
<HLASY_STRANA KSTRANA="6" HLASY="34" PROC_HLASU="10.11"/>
<HLASY_STRANA KSTRANA="7" HLASY="1" PROC_HLASU="0.29"/>
<HLASY_STRANA KSTRANA="9" HLASY="1" PROC_HLASU="0.29"/>
<HLASY_STRANA KSTRANA="10" HLASY="1" PROC_HLASU="0.29"/>
<HLASY_STRANA KSTRANA="11" HLASY="12" PROC_HLASU="3.57"/>
<HLASY_STRANA KSTRANA="15" HLASY="2" PROC_HLASU="0.59"/>
<HLASY_STRANA KSTRANA="17" HLASY="12" PROC_HLASU="3.57"/>
<HLASY_STRANA KSTRANA="18" HLASY="2" PROC_HLASU="0.59"/>
<HLASY_STRANA KSTRANA="20" HLASY="41" PROC_HLASU="12.20"/>
<HLASY_STRANA KSTRANA="21" HLASY="30" PROC_HLASU="8.92"/>
<HLASY_STRANA KSTRANA="23" HLASY="23" PROC_HLASU="6.84"/>
</OBEC>
<OBEC CIS_OBEC="539813" NAZ_OBEC="Velké Přílepy">
<UCAST OKRSKY_CELKEM="1" OKRSKY_ZPRAC="1" OKRSKY_ZPRAC_PROC="100.00" ZAPSANI_VOLICI="1943" VYDANE_OBALKY="1359" UCAST_PROC="69.94" ODEVZDANE_OBALKY="1359" PLATNE_HLASY="1354" PLATNE_HLASY_PROC="99.63" />
<HLASY_STRANA KSTRANA="1" HLASY="132" PROC_HLASU="9.74"/>
<HLASY_STRANA KSTRANA="2" HLASY="42" PROC_HLASU="3.10"/>
<HLASY_STRANA KSTRANA="3" HLASY="33" PROC_HLASU="2.43"/>
<HLASY_STRANA KSTRANA="4" HLASY="397" PROC_HLASU="29.32"/>
<HLASY_STRANA KSTRANA="5" HLASY="9" PROC_HLASU="0.66"/>
<HLASY_STRANA KSTRANA="6" HLASY="154" PROC_HLASU="11.37"/>
<HLASY_STRANA KSTRANA="9" HLASY="5" PROC_HLASU="0.36"/>
<HLASY_STRANA KSTRANA="10" HLASY="2" PROC_HLASU="0.14"/>
<HLASY_STRANA KSTRANA="11" HLASY="57" PROC_HLASU="4.20"/>
<HLASY_STRANA KSTRANA="13" HLASY="1" PROC_HLASU="0.07"/>
<HLASY_STRANA KSTRANA="15" HLASY="12" PROC_HLASU="0.88"/>
<HLASY_STRANA KSTRANA="17" HLASY="56" PROC_HLASU="4.13"/>
<HLASY_STRANA KSTRANA="18" HLASY="4" PROC_HLASU="0.29"/>
<HLASY_STRANA KSTRANA="20" HLASY="258" PROC_HLASU="19.05"/>
<HLASY_STRANA KSTRANA="21" HLASY="125" PROC_HLASU="9.23"/>
<HLASY_STRANA KSTRANA="23" HLASY="63" PROC_HLASU="4.65"/>
<HLASY_STRANA KSTRANA="24" HLASY="4" PROC_HLASU="0.29"/>
</OBEC>
<OBEC CIS_OBEC="539881" NAZ_OBEC="Zlatníky-Hodkovice">
<UCAST OKRSKY_CELKEM="1" OKRSKY_ZPRAC="1" OKRSKY_ZPRAC_PROC="100.00" ZAPSANI_VOLICI="966" VYDANE_OBALKY="611" UCAST_PROC="63.25" ODEVZDANE_OBALKY="609" PLATNE_HLASY="609" PLATNE_HLASY_PROC="100.00" />
<HLASY_STRANA KSTRANA="1" HLASY="77" PROC_HLASU="12.64"/>
<HLASY_STRANA KSTRANA="2" HLASY="12" PROC_HLASU="1.97"/>
<HLASY_STRANA KSTRANA="3" HLASY="28" PROC_HLASU="4.59"/>
<HLASY_STRANA KSTRANA="4" HLASY="115" PROC_HLASU="18.88"/>
<HLASY_STRANA KSTRANA="5" HLASY="2" PROC_HLASU="0.32"/>
<HLASY_STRANA KSTRANA="6" HLASY="47" PROC_HLASU="7.71"/>
<HLASY_STRANA KSTRANA="7" HLASY="1" PROC_HLASU="0.16"/>
<HLASY_STRANA KSTRANA="11" HLASY="29" PROC_HLASU="4.76"/>
<HLASY_STRANA KSTRANA="13" HLASY="3" PROC_HLASU="0.49"/>
<HLASY_STRANA KSTRANA="15" HLASY="3" PROC_HLASU="0.49"/>
<HLASY_STRANA KSTRANA="17" HLASY="30" PROC_HLASU="4.92"/>
<HLASY_STRANA KSTRANA="18" HLASY="2" PROC_HLASU="0.32"/>
<HLASY_STRANA KSTRANA="20" HLASY="176" PROC_HLASU="28.89"/>
<HLASY_STRANA KSTRANA="21" HLASY="61" PROC_HLASU="10.01"/>
<HLASY_STRANA KSTRANA="23" HLASY="21" PROC_HLASU="3.44"/>
<HLASY_STRANA KSTRANA="24" HLASY="2" PROC_HLASU="0.32"/>
</OBEC>
<OBEC CIS_OBEC="571199" NAZ_OBEC="Bratřínov">
<UCAST OKRSKY_CELKEM="1" OKRSKY_ZPRAC="1" OKRSKY_ZPRAC_PROC="100.00" ZAPSANI_VOLICI="132" VYDANE_OBALKY="98" UCAST_PROC="74.24" ODEVZDANE_OBALKY="98" PLATNE_HLASY="97" PLATNE_HLASY_PROC="98.98" />
<HLASY_STRANA KSTRANA="1" HLASY="9" PROC_HLASU="9.27"/>
<HLASY_STRANA KSTRANA="3" HLASY="4" PROC_HLASU="4.12"/>
<HLASY_STRANA KSTRANA="4" HLASY="17" PROC_HLASU="17.52"/>
<HLASY_STRANA KSTRANA="5" HLASY="1" PROC_HLASU="1.03"/>
<HLASY_STRANA KSTRANA="6" HLASY="15" PROC_HLASU="15.46"/>
<HLASY_STRANA KSTRANA="11" HLASY="4" PROC_HLASU="4.12"/>
<HLASY_STRANA KSTRANA="15" HLASY="1" PROC_HLASU="1.03"/>
<HLASY_STRANA KSTRANA="17" HLASY="8" PROC_HLASU="8.24"/>
<HLASY_STRANA KSTRANA="20" HLASY="28" PROC_HLASU="28.86"/>
<HLASY_STRANA KSTRANA="21" HLASY="4" PROC_HLASU="4.12"/>
<HLASY_STRANA KSTRANA="23" HLASY="6" PROC_HLASU="6.18"/>
</OBEC>
<OBEC CIS_OBEC="532991" NAZ_OBEC="Úhonice">
<UCAST OKRSKY_CELKEM="1" OKRSKY_ZPRAC="1" OKRSKY_ZPRAC_PROC="100.00" ZAPSANI_VOLICI="817" VYDANE_OBALKY="541" UCAST_PROC="66.22" ODEVZDANE_OBALKY="541" PLATNE_HLASY="539" PLATNE_HLASY_PROC="99.63" />
<HLASY_STRANA KSTRANA="1" HLASY="92" PROC_HLASU="17.06"/>
<HLASY_STRANA KSTRANA="2" HLASY="13" PROC_HLASU="2.41"/>
<HLASY_STRANA KSTRANA="3" HLASY="21" PROC_HLASU="3.89"/>
<HLASY_STRANA KSTRANA="4" HLASY="82" PROC_HLASU="15.21"/>
<HLASY_STRANA KSTRANA="5" HLASY="4" PROC_HLASU="0.74"/>
<HLASY_STRANA KSTRANA="6" HLASY="50" PROC_HLASU="9.27"/>
<HLASY_STRANA KSTRANA="10" HLASY="3" PROC_HLASU="0.55"/>
<HLASY_STRANA KSTRANA="11" HLASY="20" PROC_HLASU="3.71"/>
<HLASY_STRANA KSTRANA="13" HLASY="3" PROC_HLASU="0.55"/>
<HLASY_STRANA KSTRANA="15" HLASY="8" PROC_HLASU="1.48"/>
<HLASY_STRANA KSTRANA="17" HLASY="28" PROC_HLASU="5.19"/>
<HLASY_STRANA KSTRANA="18" HLASY="3" PROC_HLASU="0.55"/>
<HLASY_STRANA KSTRANA="20" HLASY="106" PROC_HLASU="19.66"/>
<HLASY_STRANA KSTRANA="21" HLASY="89" PROC_HLASU="16.51"/>
<HLASY_STRANA KSTRANA="23" HLASY="17" PROC_HLASU="3.15"/>
</OBEC>
<OBEC CIS_OBEC="539104" NAZ_OBEC="Bojanovice">
<UCAST OKRSKY_CELKEM="3" OKRSKY_ZPRAC="3" OKRSKY_ZPRAC_PROC="100.00" ZAPSANI_VOLICI="344" VYDANE_OBALKY="251" UCAST_PROC="72.97" ODEVZDANE_OBALKY="251" PLATNE_HLASY="251" PLATNE_HLASY_PROC="100.00" />
<HLASY_STRANA KSTRANA="1" HLASY="35" PROC_HLASU="13.94"/>
<HLASY_STRANA KSTRANA="2" HLASY="7" PROC_HLASU="2.78"/>
<HLASY_STRANA KSTRANA="3" HLASY="7" PROC_HLASU="2.78"/>
<HLASY_STRANA KSTRANA="4" HLASY="31" PROC_HLASU="12.35"/>
<HLASY_STRANA KSTRANA="5" HLASY="3" PROC_HLASU="1.19"/>
<HLASY_STRANA KSTRANA="6" HLASY="12" PROC_HLASU="4.78"/>
<HLASY_STRANA KSTRANA="9" HLASY="5" PROC_HLASU="1.99"/>
<HLASY_STRANA KSTRANA="11" HLASY="14" PROC_HLASU="5.57"/>
<HLASY_STRANA KSTRANA="13" HLASY="1" PROC_HLASU="0.39"/>
<HLASY_STRANA KSTRANA="15" HLASY="8" PROC_HLASU="3.18"/>
<HLASY_STRANA KSTRANA="17" HLASY="18" PROC_HLASU="7.17"/>
<HLASY_STRANA KSTRANA="18" HLASY="1" PROC_HLASU="0.39"/>
<HLASY_STRANA KSTRANA="20" HLASY="75" PROC_HLASU="29.88"/>
<HLASY_STRANA KSTRANA="21" HLASY="29" PROC_HLASU="11.55"/>
<HLASY_STRANA KSTRANA="23" HLASY="5" PROC_HLASU="1.99"/>
</OBEC>
<OBEC CIS_OBEC="539171" NAZ_OBEC="Dobrovíz">
<UCAST OKRSKY_CELKEM="1" OKRSKY_ZPRAC="1" OKRSKY_ZPRAC_PROC="100.00" ZAPSANI_VOLICI="412" VYDANE_OBALKY="286" UCAST_PROC="69.42" ODEVZDANE_OBALKY="286" PLATNE_HLASY="285" PLATNE_HLASY_PROC="99.65" />
<HLASY_STRANA KSTRANA="1" HLASY="44" PROC_HLASU="15.43"/>
<HLASY_STRANA KSTRANA="2" HLASY="8" PROC_HLASU="2.80"/>
<HLASY_STRANA KSTRANA="3" HLASY="6" PROC_HLASU="2.10"/>
<HLASY_STRANA KSTRANA="4" HLASY="44" PROC_HLASU="15.43"/>
<HLASY_STRANA KSTRANA="5" HLASY="2" PROC_HLASU="0.70"/>
<HLASY_STRANA KSTRANA="6" HLASY="34" PROC_HLASU="11.92"/>
<HLASY_STRANA KSTRANA="10" HLASY="2" PROC_HLASU="0.70"/>
<HLASY_STRANA KSTRANA="11" HLASY="13" PROC_HLASU="4.56"/>
<HLASY_STRANA KSTRANA="15" HLASY="1" PROC_HLASU="0.35"/>
<HLASY_STRANA KSTRANA="17" HLASY="20" PROC_HLASU="7.01"/>
<HLASY_STRANA KSTRANA="18" HLASY="3" PROC_HLASU="1.05"/>
<HLASY_STRANA KSTRANA="20" HLASY="53" PROC_HLASU="18.59"/>
<HLASY_STRANA KSTRANA="21" HLASY="47" PROC_HLASU="16.49"/>
<HLASY_STRANA KSTRANA="23" HLASY="8" PROC_HLASU="2.80"/>
</OBEC>
<OBEC CIS_OBEC="539210" NAZ_OBEC="Dolní Břežany">
<UCAST OKRSKY_CELKEM="2" OKRSKY_ZPRAC="2" OKRSKY_ZPRAC_PROC="100.00" ZAPSANI_VOLICI="2494" VYDANE_OBALKY="1727" UCAST_PROC="69.25" ODEVZDANE_OBALKY="1720" PLATNE_HLASY="1702" PLATNE_HLASY_PROC="98.95" />
<HLASY_STRANA KSTRANA="1" HLASY="127" PROC_HLASU="7.46"/>
<HLASY_STRANA KSTRANA="2" HLASY="67" PROC_HLASU="3.93"/>
<HLASY_STRANA KSTRANA="3" HLASY="47" PROC_HLASU="2.76"/>
<HLASY_STRANA KSTRANA="4" HLASY="539" PROC_HLASU="31.66"/>
<HLASY_STRANA KSTRANA="5" HLASY="2" PROC_HLASU="0.11"/>
<HLASY_STRANA KSTRANA="6" HLASY="192" PROC_HLASU="11.28"/>
<HLASY_STRANA KSTRANA="7" HLASY="1" PROC_HLASU="0.05"/>
<HLASY_STRANA KSTRANA="9" HLASY="3" PROC_HLASU="0.17"/>
<HLASY_STRANA KSTRANA="10" HLASY="4" PROC_HLASU="0.23"/>
<HLASY_STRANA KSTRANA="11" HLASY="57" PROC_HLASU="3.34"/>
<HLASY_STRANA KSTRANA="14" HLASY="1" PROC_HLASU="0.05"/>
<HLASY_STRANA KSTRANA="15" HLASY="15" PROC_HLASU="0.88"/>
<HLASY_STRANA KSTRANA="17" HLASY="59" PROC_HLASU="3.46"/>
<HLASY_STRANA KSTRANA="18" HLASY="5" PROC_HLASU="0.29"/>
<HLASY_STRANA KSTRANA="20" HLASY="369" PROC_HLASU="21.68"/>
<HLASY_STRANA KSTRANA="21" HLASY="126" PROC_HLASU="7.40"/>
<HLASY_STRANA KSTRANA="23" HLASY="88" PROC_HLASU="5.17"/>
</OBEC>
<OBEC CIS_OBEC="539287" NAZ_OBEC="Choteč">
<UCAST OKRSKY_CELKEM="1" OKRSKY_ZPRAC="1" OKRSKY_ZPRAC_PROC="100.00" ZAPSANI_VOLICI="275" VYDANE_OBALKY="167" UCAST_PROC="60.73" ODEVZDANE_OBALKY="167" PLATNE_HLASY="167" PLATNE_HLASY_PROC="100.00" />
<HLASY_STRANA KSTRANA="1" HLASY="28" PROC_HLASU="16.76"/>
<HLASY_STRANA KSTRANA="2" HLASY="3" PROC_HLASU="1.79"/>
<HLASY_STRANA KSTRANA="3" HLASY="2" PROC_HLASU="1.19"/>
<HLASY_STRANA KSTRANA="4" HLASY="37" PROC_HLASU="22.15"/>
<HLASY_STRANA KSTRANA="5" HLASY="3" PROC_HLASU="1.79"/>
<HLASY_STRANA KSTRANA="6" HLASY="22" PROC_HLASU="13.17"/>
<HLASY_STRANA KSTRANA="9" HLASY="2" PROC_HLASU="1.19"/>
<HLASY_STRANA KSTRANA="11" HLASY="1" PROC_HLASU="0.59"/>
<HLASY_STRANA KSTRANA="13" HLASY="1" PROC_HLASU="0.59"/>
<HLASY_STRANA KSTRANA="14" HLASY="1" PROC_HLASU="0.59"/>
<HLASY_STRANA KSTRANA="15" HLASY="5" PROC_HLASU="2.99"/>
<HLASY_STRANA KSTRANA="17" HLASY="10" PROC_HLASU="5.98"/>
<HLASY_STRANA KSTRANA="20" HLASY="20" PROC_HLASU="11.97"/>
<HLASY_STRANA KSTRANA="21" HLASY="26" PROC_HLASU="15.56"/>
<HLASY_STRANA KSTRANA="23" HLASY="5" PROC_HLASU="2.99"/>
<HLASY_STRANA KSTRANA="24" HLASY="1" PROC_HLASU="0.59"/>
</OBEC>
<OBEC CIS_OBEC="539562" NAZ_OBEC="Pohoří">
<UCAST OKRSKY_CELKEM="1" OKRSKY_ZPRAC="1" OKRSKY_ZPRAC_PROC="100.00" ZAPSANI_VOLICI="269" VYDANE_OBALKY="173" UCAST_PROC="64.31" ODEVZDANE_OBALKY="173" PLATNE_HLASY="172" PLATNE_HLASY_PROC="99.42" />
<HLASY_STRANA KSTRANA="1" HLASY="22" PROC_HLASU="12.79"/>
<HLASY_STRANA KSTRANA="2" HLASY="11" PROC_HLASU="6.39"/>
<HLASY_STRANA KSTRANA="3" HLASY="4" PROC_HLASU="2.32"/>
<HLASY_STRANA KSTRANA="4" HLASY="24" PROC_HLASU="13.95"/>
<HLASY_STRANA KSTRANA="5" HLASY="1" PROC_HLASU="0.58"/>
<HLASY_STRANA KSTRANA="6" HLASY="17" PROC_HLASU="9.88"/>
<HLASY_STRANA KSTRANA="9" HLASY="1" PROC_HLASU="0.58"/>
<HLASY_STRANA KSTRANA="11" HLASY="9" PROC_HLASU="5.23"/>
<HLASY_STRANA KSTRANA="15" HLASY="24" PROC_HLASU="13.95"/>
<HLASY_STRANA KSTRANA="17" HLASY="8" PROC_HLASU="4.65"/>
<HLASY_STRANA KSTRANA="20" HLASY="27" PROC_HLASU="15.69"/>
<HLASY_STRANA KSTRANA="21" HLASY="16" PROC_HLASU="9.30"/>
<HLASY_STRANA KSTRANA="23" HLASY="8" PROC_HLASU="4.65"/>
</OBEC>
<OBEC CIS_OBEC="539651" NAZ_OBEC="Řitka">
<UCAST OKRSKY_CELKEM="1" OKRSKY_ZPRAC="1" OKRSKY_ZPRAC_PROC="100.00" ZAPSANI_VOLICI="808" VYDANE_OBALKY="569" UCAST_PROC="70.42" ODEVZDANE_OBALKY="569" PLATNE_HLASY="566" PLATNE_HLASY_PROC="99.47" />
<HLASY_STRANA KSTRANA="1" HLASY="53" PROC_HLASU="9.36"/>
<HLASY_STRANA KSTRANA="2" HLASY="20" PROC_HLASU="3.53"/>
<HLASY_STRANA KSTRANA="3" HLASY="12" PROC_HLASU="2.12"/>
<HLASY_STRANA KSTRANA="4" HLASY="143" PROC_HLASU="25.26"/>
<HLASY_STRANA KSTRANA="5" HLASY="7" PROC_HLASU="1.23"/>
<HLASY_STRANA KSTRANA="6" HLASY="72" PROC_HLASU="12.72"/>
<HLASY_STRANA KSTRANA="9" HLASY="2" PROC_HLASU="0.35"/>
<HLASY_STRANA KSTRANA="10" HLASY="1" PROC_HLASU="0.17"/>
<HLASY_STRANA KSTRANA="11" HLASY="26" PROC_HLASU="4.59"/>
<HLASY_STRANA KSTRANA="13" HLASY="1" PROC_HLASU="0.17"/>
<HLASY_STRANA KSTRANA="15" HLASY="4" PROC_HLASU="0.70"/>
<HLASY_STRANA KSTRANA="17" HLASY="26" PROC_HLASU="4.59"/>
<HLASY_STRANA KSTRANA="18" HLASY="3" PROC_HLASU="0.53"/>
<HLASY_STRANA KSTRANA="20" HLASY="125" PROC_HLASU="22.08"/>
<HLASY_STRANA KSTRANA="21" HLASY="48" PROC_HLASU="8.48"/>
<HLASY_STRANA KSTRANA="23" HLASY="20" PROC_HLASU="3.53"/>
<HLASY_STRANA KSTRANA="24" HLASY="3" PROC_HLASU="0.53"/>
</OBEC>
<OBEC CIS_OBEC="539759" NAZ_OBEC="Třebotov">
<UCAST OKRSKY_CELKEM="2" OKRSKY_ZPRAC="2" OKRSKY_ZPRAC_PROC="100.00" ZAPSANI_VOLICI="1046" VYDANE_OBALKY="711" UCAST_PROC="67.97" ODEVZDANE_OBALKY="711" PLATNE_HLASY="706" PLATNE_HLASY_PROC="99.30" />
<HLASY_STRANA KSTRANA="1" HLASY="70" PROC_HLASU="9.91"/>
<HLASY_STRANA KSTRANA="2" HLASY="19" PROC_HLASU="2.69"/>
<HLASY_STRANA KSTRANA="3" HLASY="12" PROC_HLASU="1.69"/>
<HLASY_STRANA KSTRANA="4" HLASY="168" PROC_HLASU="23.79"/>
<HLASY_STRANA KSTRANA="5" HLASY="10" PROC_HLASU="1.41"/>
<HLASY_STRANA KSTRANA="6" HLASY="88" PROC_HLASU="12.46"/>
<HLASY_STRANA KSTRANA="7" HLASY="1" PROC_HLASU="0.14"/>
<HLASY_STRANA KSTRANA="9" HLASY="1" PROC_HLASU="0.14"/>
<HLASY_STRANA KSTRANA="10" HLASY="5" PROC_HLASU="0.70"/>
<HLASY_STRANA KSTRANA="11" HLASY="31" PROC_HLASU="4.39"/>
<HLASY_STRANA KSTRANA="13" HLASY="2" PROC_HLASU="0.28"/>
<HLASY_STRANA KSTRANA="14" HLASY="1" PROC_HLASU="0.14"/>
<HLASY_STRANA KSTRANA="15" HLASY="3" PROC_HLASU="0.42"/>
<HLASY_STRANA KSTRANA="17" HLASY="35" PROC_HLASU="4.95"/>
<HLASY_STRANA KSTRANA="20" HLASY="151" PROC_HLASU="21.38"/>
<HLASY_STRANA KSTRANA="21" HLASY="69" PROC_HLASU="9.77"/>
<HLASY_STRANA KSTRANA="22" HLASY="2" PROC_HLASU="0.28"/>
<HLASY_STRANA KSTRANA="23" HLASY="36" PROC_HLASU="5.09"/>
<HLASY_STRANA KSTRANA="24" HLASY="2" PROC_HLASU="0.28"/>
</OBEC>
<OBEC CIS_OBEC="539767" NAZ_OBEC="Tuchoměřice">
<UCAST OKRSKY_CELKEM="1" OKRSKY_ZPRAC="1" OKRSKY_ZPRAC_PROC="100.00" ZAPSANI_VOLICI="1020" VYDANE_OBALKY="686" UCAST_PROC="67.25" ODEVZDANE_OBALKY="679" PLATNE_HLASY="674" PLATNE_HLASY_PROC="99.26" />
<HLASY_STRANA KSTRANA="1" HLASY="89" PROC_HLASU="13.20"/>
<HLASY_STRANA KSTRANA="2" HLASY="9" PROC_HLASU="1.33"/>
<HLASY_STRANA KSTRANA="3" HLASY="23" PROC_HLASU="3.41"/>
<HLASY_STRANA KSTRANA="4" HLASY="138" PROC_HLASU="20.47"/>
<HLASY_STRANA KSTRANA="5" HLASY="2" PROC_HLASU="0.29"/>
<HLASY_STRANA KSTRANA="6" HLASY="88" PROC_HLASU="13.05"/>
<HLASY_STRANA KSTRANA="9" HLASY="5" PROC_HLASU="0.74"/>
<HLASY_STRANA KSTRANA="10" HLASY="2" PROC_HLASU="0.29"/>
<HLASY_STRANA KSTRANA="11" HLASY="24" PROC_HLASU="3.56"/>
<HLASY_STRANA KSTRANA="15" HLASY="10" PROC_HLASU="1.48"/>
<HLASY_STRANA KSTRANA="17" HLASY="36" PROC_HLASU="5.34"/>
<HLASY_STRANA KSTRANA="18" HLASY="5" PROC_HLASU="0.74"/>
<HLASY_STRANA KSTRANA="20" HLASY="139" PROC_HLASU="20.62"/>
<HLASY_STRANA KSTRANA="21" HLASY="70" PROC_HLASU="10.38"/>
<HLASY_STRANA KSTRANA="22" HLASY="1" PROC_HLASU="0.14"/>
<HLASY_STRANA KSTRANA="23" HLASY="33" PROC_HLASU="4.89"/>
</OBEC>
<OBEC CIS_OBEC="539902" NAZ_OBEC="Zvole">
<UCAST OKRSKY_CELKEM="1" OKRSKY_ZPRAC="1" OKRSKY_ZPRAC_PROC="100.00" ZAPSANI_VOLICI="1189" VYDANE_OBALKY="842" UCAST_PROC="70.82" ODEVZDANE_OBALKY="842" PLATNE_HLASY="837" PLATNE_HLASY_PROC="99.41" />
<HLASY_STRANA KSTRANA="1" HLASY="78" PROC_HLASU="9.31"/>
<HLASY_STRANA KSTRANA="2" HLASY="41" PROC_HLASU="4.89"/>
<HLASY_STRANA KSTRANA="3" HLASY="12" PROC_HLASU="1.43"/>
<HLASY_STRANA KSTRANA="4" HLASY="254" PROC_HLASU="30.34"/>
<HLASY_STRANA KSTRANA="5" HLASY="3" PROC_HLASU="0.35"/>
<HLASY_STRANA KSTRANA="6" HLASY="110" PROC_HLASU="13.14"/>
<HLASY_STRANA KSTRANA="9" HLASY="3" PROC_HLASU="0.35"/>
<HLASY_STRANA KSTRANA="10" HLASY="3" PROC_HLASU="0.35"/>
<HLASY_STRANA KSTRANA="11" HLASY="30" PROC_HLASU="3.58"/>
<HLASY_STRANA KSTRANA="13" HLASY="2" PROC_HLASU="0.23"/>
<HLASY_STRANA KSTRANA="14" HLASY="1" PROC_HLASU="0.11"/>
<HLASY_STRANA KSTRANA="15" HLASY="9" PROC_HLASU="1.07"/>
<HLASY_STRANA KSTRANA="17" HLASY="28" PROC_HLASU="3.34"/>
<HLASY_STRANA KSTRANA="18" HLASY="2" PROC_HLASU="0.23"/>
<HLASY_STRANA KSTRANA="20" HLASY="193" PROC_HLASU="23.05"/>
<HLASY_STRANA KSTRANA="21" HLASY="41" PROC_HLASU="4.89"/>
<HLASY_STRANA KSTRANA="23" HLASY="27" PROC_HLASU="3.22"/>
</OBEC>
<OBEC CIS_OBEC="571351" NAZ_OBEC="Úholičky">
<UCAST OKRSKY_CELKEM="1" OKRSKY_ZPRAC="1" OKRSKY_ZPRAC_PROC="100.00" ZAPSANI_VOLICI="568" VYDANE_OBALKY="390" UCAST_PROC="68.66" ODEVZDANE_OBALKY="390" PLATNE_HLASY="388" PLATNE_HLASY_PROC="99.49" />
<HLASY_STRANA KSTRANA="1" HLASY="44" PROC_HLASU="11.34"/>
<HLASY_STRANA KSTRANA="2" HLASY="9" PROC_HLASU="2.31"/>
<HLASY_STRANA KSTRANA="3" HLASY="7" PROC_HLASU="1.80"/>
<HLASY_STRANA KSTRANA="4" HLASY="96" PROC_HLASU="24.74"/>
<HLASY_STRANA KSTRANA="5" HLASY="7" PROC_HLASU="1.80"/>
<HLASY_STRANA KSTRANA="6" HLASY="33" PROC_HLASU="8.50"/>
<HLASY_STRANA KSTRANA="7" HLASY="1" PROC_HLASU="0.25"/>
<HLASY_STRANA KSTRANA="9" HLASY="1" PROC_HLASU="0.25"/>
<HLASY_STRANA KSTRANA="11" HLASY="17" PROC_HLASU="4.38"/>
<HLASY_STRANA KSTRANA="13" HLASY="2" PROC_HLASU="0.51"/>
<HLASY_STRANA KSTRANA="15" HLASY="6" PROC_HLASU="1.54"/>
<HLASY_STRANA KSTRANA="17" HLASY="15" PROC_HLASU="3.86"/>
<HLASY_STRANA KSTRANA="18" HLASY="2" PROC_HLASU="0.51"/>
<HLASY_STRANA KSTRANA="20" HLASY="72" PROC_HLASU="18.55"/>
<HLASY_STRANA KSTRANA="21" HLASY="51" PROC_HLASU="13.14"/>
<HLASY_STRANA KSTRANA="23" HLASY="25" PROC_HLASU="6.44"/>
</OBEC>
<OBEC CIS_OBEC="599727" NAZ_OBEC="Karlík">
<UCAST OKRSKY_CELKEM="1" OKRSKY_ZPRAC="1" OKRSKY_ZPRAC_PROC="100.00" ZAPSANI_VOLICI="360" VYDANE_OBALKY="259" UCAST_PROC="71.94" ODEVZDANE_OBALKY="259" PLATNE_HLASY="259" PLATNE_HLASY_PROC="100.00" />
<HLASY_STRANA KSTRANA="1" HLASY="24" PROC_HLASU="9.26"/>
<HLASY_STRANA KSTRANA="2" HLASY="9" PROC_HLASU="3.47"/>
<HLASY_STRANA KSTRANA="3" HLASY="6" PROC_HLASU="2.31"/>
<HLASY_STRANA KSTRANA="4" HLASY="52" PROC_HLASU="20.07"/>
<HLASY_STRANA KSTRANA="5" HLASY="7" PROC_HLASU="2.70"/>
<HLASY_STRANA KSTRANA="6" HLASY="44" PROC_HLASU="16.98"/>
<HLASY_STRANA KSTRANA="9" HLASY="1" PROC_HLASU="0.38"/>
<HLASY_STRANA KSTRANA="10" HLASY="1" PROC_HLASU="0.38"/>
<HLASY_STRANA KSTRANA="11" HLASY="10" PROC_HLASU="3.86"/>
<HLASY_STRANA KSTRANA="13" HLASY="3" PROC_HLASU="1.15"/>
<HLASY_STRANA KSTRANA="15" HLASY="2" PROC_HLASU="0.77"/>
<HLASY_STRANA KSTRANA="17" HLASY="10" PROC_HLASU="3.86"/>
<HLASY_STRANA KSTRANA="18" HLASY="1" PROC_HLASU="0.38"/>
<HLASY_STRANA KSTRANA="20" HLASY="56" PROC_HLASU="21.62"/>
<HLASY_STRANA KSTRANA="21" HLASY="23" PROC_HLASU="8.88"/>
<HLASY_STRANA KSTRANA="23" HLASY="9" PROC_HLASU="3.47"/>
<HLASY_STRANA KSTRANA="24" HLASY="1" PROC_HLASU="0.38"/>
</OBEC>
<OBEC CIS_OBEC="539368" NAZ_OBEC="Kamenný Přívoz">
<UCAST OKRSKY_CELKEM="1" OKRSKY_ZPRAC="1" OKRSKY_ZPRAC_PROC="100.00" ZAPSANI_VOLICI="1087" VYDANE_OBALKY="633" UCAST_PROC="58.23" ODEVZDANE_OBALKY="633" PLATNE_HLASY="626" PLATNE_HLASY_PROC="98.89" />
<HLASY_STRANA KSTRANA="1" HLASY="109" PROC_HLASU="17.41"/>
<HLASY_STRANA KSTRANA="2" HLASY="12" PROC_HLASU="1.91"/>
<HLASY_STRANA KSTRANA="3" HLASY="13" PROC_HLASU="2.07"/>
<HLASY_STRANA KSTRANA="4" HLASY="81" PROC_HLASU="12.93"/>
<HLASY_STRANA KSTRANA="5" HLASY="2" PROC_HLASU="0.31"/>
<HLASY_STRANA KSTRANA="6" HLASY="48" PROC_HLASU="7.66"/>
<HLASY_STRANA KSTRANA="9" HLASY="5" PROC_HLASU="0.79"/>
<HLASY_STRANA KSTRANA="10" HLASY="3" PROC_HLASU="0.47"/>
<HLASY_STRANA KSTRANA="11" HLASY="13" PROC_HLASU="2.07"/>
<HLASY_STRANA KSTRANA="13" HLASY="2" PROC_HLASU="0.31"/>
<HLASY_STRANA KSTRANA="15" HLASY="11" PROC_HLASU="1.75"/>
<HLASY_STRANA KSTRANA="17" HLASY="30" PROC_HLASU="4.79"/>
<HLASY_STRANA KSTRANA="18" HLASY="4" PROC_HLASU="0.63"/>
<HLASY_STRANA KSTRANA="20" HLASY="155" PROC_HLASU="24.76"/>
<HLASY_STRANA KSTRANA="21" HLASY="98" PROC_HLASU="15.65"/>
<HLASY_STRANA KSTRANA="22" HLASY="1" PROC_HLASU="0.15"/>
<HLASY_STRANA KSTRANA="23" HLASY="39" PROC_HLASU="6.23"/>
</OBEC>
<OBEC CIS_OBEC="539732" NAZ_OBEC="Štěchovice">
<UCAST OKRSKY_CELKEM="3" OKRSKY_ZPRAC="3" OKRSKY_ZPRAC_PROC="100.00" ZAPSANI_VOLICI="1470" VYDANE_OBALKY="992" UCAST_PROC="67.48" ODEVZDANE_OBALKY="992" PLATNE_HLASY="984" PLATNE_HLASY_PROC="99.19" />
<HLASY_STRANA KSTRANA="1" HLASY="146" PROC_HLASU="14.83"/>
<HLASY_STRANA KSTRANA="2" HLASY="38" PROC_HLASU="3.86"/>
<HLASY_STRANA KSTRANA="3" HLASY="35" PROC_HLASU="3.55"/>
<HLASY_STRANA KSTRANA="4" HLASY="188" PROC_HLASU="19.10"/>
<HLASY_STRANA KSTRANA="5" HLASY="13" PROC_HLASU="1.32"/>
<HLASY_STRANA KSTRANA="6" HLASY="120" PROC_HLASU="12.19"/>
<HLASY_STRANA KSTRANA="7" HLASY="1" PROC_HLASU="0.10"/>
<HLASY_STRANA KSTRANA="9" HLASY="5" PROC_HLASU="0.50"/>
<HLASY_STRANA KSTRANA="10" HLASY="3" PROC_HLASU="0.30"/>
<HLASY_STRANA KSTRANA="11" HLASY="35" PROC_HLASU="3.55"/>
<HLASY_STRANA KSTRANA="13" HLASY="1" PROC_HLASU="0.10"/>
<HLASY_STRANA KSTRANA="14" HLASY="1" PROC_HLASU="0.10"/>
<HLASY_STRANA KSTRANA="15" HLASY="9" PROC_HLASU="0.91"/>
<HLASY_STRANA KSTRANA="17" HLASY="54" PROC_HLASU="5.48"/>
<HLASY_STRANA KSTRANA="18" HLASY="5" PROC_HLASU="0.50"/>
<HLASY_STRANA KSTRANA="20" HLASY="200" PROC_HLASU="20.32"/>
<HLASY_STRANA KSTRANA="21" HLASY="85" PROC_HLASU="8.63"/>
<HLASY_STRANA KSTRANA="23" HLASY="42" PROC_HLASU="4.26"/>
<HLASY_STRANA KSTRANA="24" HLASY="3" PROC_HLASU="0.30"/>
</OBEC>
<OBEC CIS_OBEC="539848" NAZ_OBEC="Vrané nad Vltavou">
<UCAST OKRSKY_CELKEM="2" OKRSKY_ZPRAC="2" OKRSKY_ZPRAC_PROC="100.00" ZAPSANI_VOLICI="1846" VYDANE_OBALKY="1174" UCAST_PROC="63.60" ODEVZDANE_OBALKY="1173" PLATNE_HLASY="1160" PLATNE_HLASY_PROC="98.89" />
<HLASY_STRANA KSTRANA="1" HLASY="130" PROC_HLASU="11.20"/>
<HLASY_STRANA KSTRANA="2" HLASY="39" PROC_HLASU="3.36"/>
<HLASY_STRANA KSTRANA="3" HLASY="44" PROC_HLASU="3.79"/>
<HLASY_STRANA KSTRANA="4" HLASY="254" PROC_HLASU="21.89"/>
<HLASY_STRANA KSTRANA="5" HLASY="6" PROC_HLASU="0.51"/>
<HLASY_STRANA KSTRANA="6" HLASY="118" PROC_HLASU="10.17"/>
<HLASY_STRANA KSTRANA="9" HLASY="5" PROC_HLASU="0.43"/>
<HLASY_STRANA KSTRANA="10" HLASY="1" PROC_HLASU="0.08"/>
<HLASY_STRANA KSTRANA="11" HLASY="44" PROC_HLASU="3.79"/>
<HLASY_STRANA KSTRANA="13" HLASY="4" PROC_HLASU="0.34"/>
<HLASY_STRANA KSTRANA="15" HLASY="8" PROC_HLASU="0.68"/>
<HLASY_STRANA KSTRANA="17" HLASY="55" PROC_HLASU="4.74"/>
<HLASY_STRANA KSTRANA="18" HLASY="1" PROC_HLASU="0.08"/>
<HLASY_STRANA KSTRANA="20" HLASY="246" PROC_HLASU="21.20"/>
<HLASY_STRANA KSTRANA="21" HLASY="113" PROC_HLASU="9.74"/>
<HLASY_STRANA KSTRANA="22" HLASY="1" PROC_HLASU="0.08"/>
<HLASY_STRANA KSTRANA="23" HLASY="90" PROC_HLASU="7.75"/>
<HLASY_STRANA KSTRANA="24" HLASY="1" PROC_HLASU="0.08"/>
</OBEC>
<OBEC CIS_OBEC="540765" NAZ_OBEC="Mníšek pod Brdy">
<UCAST OKRSKY_CELKEM="5" OKRSKY_ZPRAC="5" OKRSKY_ZPRAC_PROC="100.00" ZAPSANI_VOLICI="4020" VYDANE_OBALKY="2624" UCAST_PROC="65.27" ODEVZDANE_OBALKY="2624" PLATNE_HLASY="2594" PLATNE_HLASY_PROC="98.86" />
<HLASY_STRANA KSTRANA="1" HLASY="362" PROC_HLASU="13.95"/>
<HLASY_STRANA KSTRANA="2" HLASY="70" PROC_HLASU="2.69"/>
<HLASY_STRANA KSTRANA="3" HLASY="109" PROC_HLASU="4.20"/>
<HLASY_STRANA KSTRANA="4" HLASY="584" PROC_HLASU="22.51"/>
<HLASY_STRANA KSTRANA="5" HLASY="10" PROC_HLASU="0.38"/>
<HLASY_STRANA KSTRANA="6" HLASY="279" PROC_HLASU="10.75"/>
<HLASY_STRANA KSTRANA="7" HLASY="2" PROC_HLASU="0.07"/>
<HLASY_STRANA KSTRANA="9" HLASY="19" PROC_HLASU="0.73"/>
<HLASY_STRANA KSTRANA="10" HLASY="8" PROC_HLASU="0.30"/>
<HLASY_STRANA KSTRANA="11" HLASY="130" PROC_HLASU="5.01"/>
<HLASY_STRANA KSTRANA="13" HLASY="6" PROC_HLASU="0.23"/>
<HLASY_STRANA KSTRANA="14" HLASY="2" PROC_HLASU="0.07"/>
<HLASY_STRANA KSTRANA="15" HLASY="25" PROC_HLASU="0.96"/>
<HLASY_STRANA KSTRANA="17" HLASY="127" PROC_HLASU="4.89"/>
<HLASY_STRANA KSTRANA="18" HLASY="18" PROC_HLASU="0.69"/>
<HLASY_STRANA KSTRANA="20" HLASY="422" PROC_HLASU="16.26"/>
<HLASY_STRANA KSTRANA="21" HLASY="254" PROC_HLASU="9.79"/>
<HLASY_STRANA KSTRANA="22" HLASY="3" PROC_HLASU="0.11"/>
<HLASY_STRANA KSTRANA="23" HLASY="153" PROC_HLASU="5.89"/>
<HLASY_STRANA KSTRANA="24" HLASY="11" PROC_HLASU="0.42"/>
</OBEC>
<OBEC CIS_OBEC="571261" NAZ_OBEC="Kytín">
<UCAST OKRSKY_CELKEM="1" OKRSKY_ZPRAC="1" OKRSKY_ZPRAC_PROC="100.00" ZAPSANI_VOLICI="418" VYDANE_OBALKY="323" UCAST_PROC="77.27" ODEVZDANE_OBALKY="323" PLATNE_HLASY="317" PLATNE_HLASY_PROC="98.14" />
<HLASY_STRANA KSTRANA="1" HLASY="56" PROC_HLASU="17.66"/>
<HLASY_STRANA KSTRANA="2" HLASY="7" PROC_HLASU="2.20"/>
<HLASY_STRANA KSTRANA="3" HLASY="10" PROC_HLASU="3.15"/>
<HLASY_STRANA KSTRANA="4" HLASY="75" PROC_HLASU="23.65"/>
<HLASY_STRANA KSTRANA="5" HLASY="3" PROC_HLASU="0.94"/>
<HLASY_STRANA KSTRANA="6" HLASY="38" PROC_HLASU="11.98"/>
<HLASY_STRANA KSTRANA="10" HLASY="1" PROC_HLASU="0.31"/>
<HLASY_STRANA KSTRANA="11" HLASY="13" PROC_HLASU="4.10"/>
<HLASY_STRANA KSTRANA="13" HLASY="1" PROC_HLASU="0.31"/>
<HLASY_STRANA KSTRANA="15" HLASY="8" PROC_HLASU="2.52"/>
<HLASY_STRANA KSTRANA="17" HLASY="10" PROC_HLASU="3.15"/>
<HLASY_STRANA KSTRANA="18" HLASY="2" PROC_HLASU="0.63"/>
<HLASY_STRANA KSTRANA="20" HLASY="65" PROC_HLASU="20.50"/>
<HLASY_STRANA KSTRANA="21" HLASY="21" PROC_HLASU="6.62"/>
<HLASY_STRANA KSTRANA="23" HLASY="7" PROC_HLASU="2.20"/>
</OBEC>
<OBEC CIS_OBEC="571326" NAZ_OBEC="Lichoceves">
<UCAST OKRSKY_CELKEM="2" OKRSKY_ZPRAC="2" OKRSKY_ZPRAC_PROC="100.00" ZAPSANI_VOLICI="284" VYDANE_OBALKY="198" UCAST_PROC="69.72" ODEVZDANE_OBALKY="198" PLATNE_HLASY="196" PLATNE_HLASY_PROC="98.99" />
<HLASY_STRANA KSTRANA="1" HLASY="20" PROC_HLASU="10.20"/>
<HLASY_STRANA KSTRANA="2" HLASY="3" PROC_HLASU="1.53"/>
<HLASY_STRANA KSTRANA="3" HLASY="6" PROC_HLASU="3.06"/>
<HLASY_STRANA KSTRANA="4" HLASY="45" PROC_HLASU="22.95"/>
<HLASY_STRANA KSTRANA="5" HLASY="1" PROC_HLASU="0.51"/>
<HLASY_STRANA KSTRANA="6" HLASY="10" PROC_HLASU="5.10"/>
<HLASY_STRANA KSTRANA="7" HLASY="1" PROC_HLASU="0.51"/>
<HLASY_STRANA KSTRANA="10" HLASY="1" PROC_HLASU="0.51"/>
<HLASY_STRANA KSTRANA="11" HLASY="11" PROC_HLASU="5.61"/>
<HLASY_STRANA KSTRANA="13" HLASY="1" PROC_HLASU="0.51"/>
<HLASY_STRANA KSTRANA="17" HLASY="11" PROC_HLASU="5.61"/>
<HLASY_STRANA KSTRANA="18" HLASY="1" PROC_HLASU="0.51"/>
<HLASY_STRANA KSTRANA="20" HLASY="44" PROC_HLASU="22.44"/>
<HLASY_STRANA KSTRANA="21" HLASY="32" PROC_HLASU="16.32"/>
<HLASY_STRANA KSTRANA="23" HLASY="8" PROC_HLASU="4.08"/>
<HLASY_STRANA KSTRANA="24" HLASY="1" PROC_HLASU="0.51"/>
</OBEC>
<OBEC CIS_OBEC="571334" NAZ_OBEC="Okoř">
<UCAST OKRSKY_CELKEM="1" OKRSKY_ZPRAC="1" OKRSKY_ZPRAC_PROC="100.00" ZAPSANI_VOLICI="83" VYDANE_OBALKY="59" UCAST_PROC="71.08" ODEVZDANE_OBALKY="59" PLATNE_HLASY="57" PLATNE_HLASY_PROC="96.61" />
<HLASY_STRANA KSTRANA="1" HLASY="6" PROC_HLASU="10.52"/>
<HLASY_STRANA KSTRANA="2" HLASY="2" PROC_HLASU="3.50"/>
<HLASY_STRANA KSTRANA="3" HLASY="1" PROC_HLASU="1.75"/>
<HLASY_STRANA KSTRANA="4" HLASY="16" PROC_HLASU="28.07"/>
<HLASY_STRANA KSTRANA="6" HLASY="9" PROC_HLASU="15.78"/>
<HLASY_STRANA KSTRANA="11" HLASY="1" PROC_HLASU="1.75"/>
<HLASY_STRANA KSTRANA="17" HLASY="3" PROC_HLASU="5.26"/>
<HLASY_STRANA KSTRANA="18" HLASY="1" PROC_HLASU="1.75"/>
<HLASY_STRANA KSTRANA="20" HLASY="14" PROC_HLASU="24.56"/>
<HLASY_STRANA KSTRANA="21" HLASY="2" PROC_HLASU="3.50"/>
<HLASY_STRANA KSTRANA="23" HLASY="2" PROC_HLASU="3.50"/>
</OBEC>
<OBEC CIS_OBEC="571342" NAZ_OBEC="Svrkyně">
<UCAST OKRSKY_CELKEM="1" OKRSKY_ZPRAC="1" OKRSKY_ZPRAC_PROC="100.00" ZAPSANI_VOLICI="232" VYDANE_OBALKY="143" UCAST_PROC="61.64" ODEVZDANE_OBALKY="143" PLATNE_HLASY="143" PLATNE_HLASY_PROC="100.00" />
<HLASY_STRANA KSTRANA="1" HLASY="16" PROC_HLASU="11.18"/>
<HLASY_STRANA KSTRANA="3" HLASY="2" PROC_HLASU="1.39"/>
<HLASY_STRANA KSTRANA="4" HLASY="38" PROC_HLASU="26.57"/>
<HLASY_STRANA KSTRANA="6" HLASY="12" PROC_HLASU="8.39"/>
<HLASY_STRANA KSTRANA="11" HLASY="4" PROC_HLASU="2.79"/>
<HLASY_STRANA KSTRANA="15" HLASY="1" PROC_HLASU="0.69"/>
<HLASY_STRANA KSTRANA="17" HLASY="12" PROC_HLASU="8.39"/>
<HLASY_STRANA KSTRANA="20" HLASY="26" PROC_HLASU="18.18"/>
<HLASY_STRANA KSTRANA="21" HLASY="25" PROC_HLASU="17.48"/>
<HLASY_STRANA KSTRANA="23" HLASY="7" PROC_HLASU="4.89"/>
</OBEC>
</VYSLEDKY_OKRES>
